Workbook

Sheet Summary
A1: ADAS Test Execution Tracker, Technical Test Suite and UAT
A2: Eight technical testing activities carry the cleansed and completed test suite. Usability and UAT retain the continuous role-based journeys, the shared participant-stage execution log, SUS, defects, traceability, and formal acceptance gates. See the Cleansing Log tab for every retention, rewrite, reclassification, and removal decision.
A4: Activity | B4: Planned Cases / Executions | C4: Pass | D4: Fail | E4: Blocked | F4: Retest | G4: Notes
A5: Unit Testing | B5: =COUNTIF('Unit Testing'!A2:A400,"<>") -> 68 | C5: =COUNTIF('Unit Testing'!G2:G400,"Pass") -> 68 | D5: =COUNTIF('Unit Testing'!G2:G400,"Fail") -> 0 | E5: =COUNTIF('Unit Testing'!G2:G400,"Blocked") -> 0 | F5: =COUNTIF('Unit Testing'!G2:G400,"Retest") -> 0 | G5: Technical activity
A6: Integration Testing | B6: =COUNTIF('Integration Testing'!A2:A400,"<>") -> 23 | C6: =COUNTIF('Integration Testing'!G2:G400,"Pass") -> 23 | D6: =COUNTIF('Integration Testing'!G2:G400,"Fail") -> 0 | E6: =COUNTIF('Integration Testing'!G2:G400,"Blocked") -> 0 | F6: =COUNTIF('Integration Testing'!G2:G400,"Retest") -> 0 | G6: Technical activity
A7: System E2E Testing | B7: =COUNTIF('System E2E Testing'!A2:A400,"<>") -> 21 | C7: =COUNTIF('System E2E Testing'!G2:G400,"Pass") -> 21 | D7: =COUNTIF('System E2E Testing'!G2:G400,"Fail") -> 0 | E7: =COUNTIF('System E2E Testing'!G2:G400,"Blocked") -> 0 | F7: =COUNTIF('System E2E Testing'!G2:G400,"Retest") -> 0 | G7: Technical activity
A8: AI Model Validation | B8: =COUNTIF('AI Model Validation'!A2:A399,"<>") -> 9 | C8: =COUNTIF('AI Model Validation'!G2:G399,"Pass") -> 9 | D8: =COUNTIF('AI Model Validation'!G2:G399,"Fail") -> 0 | E8: =COUNTIF('AI Model Validation'!G2:G399,"Blocked") -> 0 | F8: =COUNTIF('AI Model Validation'!G2:G399,"Retest") -> 0 | G8: Technical activity
A9: Performance & Load Testing | B9: =COUNTIF('Performance & Load Testing'!A2:A399,"<>") -> 15 | C9: =COUNTIF('Performance & Load Testing'!G2:G399,"Pass") -> 15 | D9: =COUNTIF('Performance & Load Testing'!G2:G399,"Fail") -> 0 | E9: =COUNTIF('Performance & Load Testing'!G2:G399,"Blocked") -> 0 | F9: =COUNTIF('Performance & Load Testing'!G2:G399,"Retest") -> 0 | G9: Technical activity
A10: Reliability & Endurance | B10: =COUNTIF('Reliability & Endurance'!A2:A400,"<>") -> 15 | C10: =COUNTIF('Reliability & Endurance'!G2:G400,"Pass") -> 15 | D10: =COUNTIF('Reliability & Endurance'!G2:G400,"Fail") -> 0 | E10: =COUNTIF('Reliability & Endurance'!G2:G400,"Blocked") -> 0 | F10: =COUNTIF('Reliability & Endurance'!G2:G400,"Retest") -> 0 | G10: Technical activity
A11: Backup & Recovery | B11: =COUNTIF('Backup & Recovery'!A2:A400,"<>") -> 16 | C11: =COUNTIF('Backup & Recovery'!G2:G400,"Pass") -> 16 | D11: =COUNTIF('Backup & Recovery'!G2:G400,"Fail") -> 0 | E11: =COUNTIF('Backup & Recovery'!G2:G400,"Blocked") -> 0 | F11: =COUNTIF('Backup & Recovery'!G2:G400,"Retest") -> 0 | G11: Technical prerequisite for Administrator recovery journey
A12: Security Testing | B12: =COUNTIF('Security Testing'!A2:A28,"<>") -> 27 | C12: =COUNTIF('Security Testing'!G2:G28,"Pass") -> 27 | D12: =COUNTIF('Security Testing'!G2:G28,"Fail") -> 0 | E12: =COUNTIF('Security Testing'!G2:G28,"Blocked") -> 0 | F12: =COUNTIF('Security Testing'!G2:G28,"Retest") -> 0 | G12: Technical prerequisite for RBAC/audit acceptance
A13: Usability + UAT Participant Stages | B13: =COUNTA('Execution Log'!A2:A34) -> 33 | C13: =COUNTIF('Execution Log'!C2:C34,"Pass") -> 33 | D13: =COUNTIF('Execution Log'!C2:C34,"Fail") -> 0 | E13: =COUNTIF('Execution Log'!C2:C34,"Blocked") -> 0 | F13: =COUNTIF('Execution Log'!C2:C34,"Retest Required") -> 0 | G13: One row per participant-stage execution
A14: SUS Questionnaire | B14: 4 | C14: =COUNTIF('SUS Questionnaire'!N5:N8,">=68") -> 4 | D14: =COUNTIF('SUS Questionnaire'!N5:N8,"<68") -> 0 | G14: Per-participant score. The overall criterion uses the mean.
A15: Formal UAT Acceptance | B15: 1 | C15: =IF('UAT Results'!B13="ELIGIBLE FOR FORMAL SIGN-OFF",1,0) -> 1 | G15: See UAT Results and separate sign-off document
A16: Technical test cases, all eight activities | B16: =SUM(B5:B12) -> 194 | C16: =SUM(C5:C12) -> 194 | D16: =SUM(D5:D12) -> 0 | E16: =SUM(E5:E12) -> 0 | F16: =SUM(F5:F12) -> 0 | G16: Blank Result means the case has not yet been executed. No result is pre-populated.
A18: NEW ADDITION PROPOSED BY CODEX, UAT ACCEPTANCE RULE
A19: Denominator: all 33 planned applicable participant-stage executions (27 Operator and 6 Administrator). Not Executed, Blocked, and Retest Required do not count as passes. Blocked and Retest Required remain unresolved and prevent full completion.
A20: Eligibility requires all 33 executions completed, at least 95% passed, zero open Critical or Major defects, a SUS overall mean of at least 68, all readiness items marked Ready, and the separate formal sign-off completed by the authorized representative.
A21: Why added: participant-stage execution is the smallest consistent unit already required for timings, assistance observations, and evidence. It prevents incomplete participant stages from being omitted from the acceptance denominator.
A22: This is a proposed control and should be carried into the consolidated test plan if the team approves it.
A24: UAT Key Metric | B24: Current Value | C24: Target / Interpretation
A25: Planned participant-stage executions | B25: ='UAT Results'!B4 -> 33 | C25: 33
A26: Completed participant-stage executions | B26: ='UAT Results'!B5 -> 33 | C26: 33
A27: Participant-stage pass rate | B27: ='UAT Results'!B7 -> 1 | C27: >=95%
A28: Open Critical or Major defects | B28: ='UAT Results'!B10 -> 0 | C28: 0
A29: Overall SUS mean | B29: ='UAT Results'!B11 -> 89.375 | C29: >=68
A30: Readiness items marked Ready | B30: ='UAT Results'!B12 -> 9 | C30: 9 of 9
A31: Eligibility for formal sign-off | B31: ='UAT Results'!B13 -> ELIGIBLE FOR FORMAL SIGN-OFF | C31: Eligible only when every gate above passes
A32: Recorded acceptance decision | B32: ='UAT Results'!B14 -> Accepted | C32: Pending / Accepted / Accepted with Conditions / Rejected

Sheet Unit Testing
A1: Test ID | B1: Requirement / Objective | C1: Scenario | D1: Preconditions / Steps | E1: Expected Result / Acceptance | F1: Date Executed | G1: Result | H1: Actual Result / Notes | I1: Evidence Link | J1: Defect / Retest Note
A2: TC-UNIT-001 | B2: FR-01 User Authentication | C2: Valid credentials establish a server session without exposing a token. | D2: 1. Run the automated unit selector: uv run pytest backend/tests/test_auth.py::TestLogin::test_login_success_sets_cookie_no_token_in_body 2. Confirm the selected test passes and capture the run output. | E2: A successful login returns the protected session cookie and no token in the response body. | F2: 46261 | G2: Pass | H2: Pass, full backend fast suite: 939 passed, 2 skipped, 12 deselected. | I2: https://docs.google.com/spreadsheets/d/1MZ4a0eA8IWucgHC-uYO-hEZ9kHk3JJnZqukghApCnXs/edit?gid=0#gid=0&range=A2:J2 | J2: No defect.
A3: TC-UNIT-002 | B3: FR-01 User Authentication | C3: Invalid credentials receive a non-enumerating denial. | D3: 1. Run the automated unit selector: uv run pytest backend/tests/test_auth.py::TestLogin::test_bad_credentials_return_generic_401 2. Confirm the selected test passes and capture the run output. | E3: Incorrect credentials return the generic 401 (not signed in) response. | F3: 46261 | G3: Pass | H3: Pass, full backend fast suite: 939 passed, 2 skipped, 12 deselected. | I3: https://docs.google.com/spreadsheets/d/1MZ4a0eA8IWucgHC-uYO-hEZ9kHk3JJnZqukghApCnXs/edit?gid=0#gid=0&range=A3:J3 | J3: No defect.
A4: TC-UNIT-003 | B4: FR-02 Role-Based Access Control (RBAC) | C4: Role-aware navigation omits Administrator destinations for an Operator identity. | D4: 1. Run the automated unit selectors: pnpm --filter frontend test:run src/components/layouts/Sidebar.tracker.test.tsx pnpm --filter frontend test:run src/components/layouts/Sidebar.test.tsx | E4: 1. With the Operator identity, User Management, AI Performance, Audit Log, and Maintenance are absent from the rendered output rather than merely hidden by style. 2. With the Administrator identity, all four destinations are present. | F4: 46261 | G4: Pass | H4: Both acceptance conditions observed. With an Operator identity in state, Users, AI Performance, Audit Log and Maintenance were each absent from the rendered DOM, asserted with queryByText rather than a style check, while Dashboard still rendered so the result is not an empty-render false negative. With an Administrator identity all four destinations rendered. 14 frontend tests passed. | I4: https://docs.google.com/spreadsheets/d/1MZ4a0eA8IWucgHC-uYO-hEZ9kHk3JJnZqukghApCnXs/edit?gid=0#gid=0&range=A4:J4 | J4: No additional defect note was recorded in the tracker.
A5: TC-UNIT-004 | B5: FR-03 User Account Management | C5: An Administrator creates an Operator account. | D5: 1. Run the automated unit selector: uv run pytest backend/tests/test_users.py::TestCreateUser::test_admin_creates_operator 2. Confirm the selected test passes and capture the run output. | E5: A valid Operator account is created with the requested role. | F5: 46261 | G5: Pass | H5: Pass, full backend fast suite: 939 passed, 2 skipped, 12 deselected. | I5: https://docs.google.com/spreadsheets/d/1MZ4a0eA8IWucgHC-uYO-hEZ9kHk3JJnZqukghApCnXs/edit?gid=0#gid=0&range=A5:J5 | J5: No defect.
A6: TC-UNIT-005 | B6: FR-03 User Account Management | C6: The final Administrator account cannot be deleted. | D6: 1. Run the automated unit selector: uv run pytest backend/tests/test_users.py::TestDeleteUser::test_cannot_delete_last_admin 2. Confirm the selected test passes and capture the run output. | E6: The protected last-admin account remains available and the operation is rejected. | F6: 46261 | G6: Pass | H6: Pass, full backend fast suite: 939 passed, 2 skipped, 12 deselected. | I6: https://docs.google.com/spreadsheets/d/1MZ4a0eA8IWucgHC-uYO-hEZ9kHk3JJnZqukghApCnXs/edit?gid=0#gid=0&range=A6:J6 | J6: No defect.
A7: TC-UNIT-006 | B7: FR-03 User Account Management | C7: The password policy validator enforces the documented minimum length and digit rule. | D7: 1. Run the automated unit selectors: uv run pytest backend/tests/test_tc_unit_users.py::TestPasswordPolicy uv run pytest backend/tests/test_auth.py::TestBoundaryValues::test_password_length_boundary 2. Confirm accept/reject per candidate and inspect the 422 response body. | E7: 1. 'Passw0rd' is accepted. 2. 'short1' (under 8 characters), 'passwordonly' (no digit), and the empty string are each rejected with the corresponding field error. 3. No password value appears in the returned error text. | F7: 46261 | G7: Pass | H7: Pass. Passw0rd was accepted. short1, passwordonly, and empty input were rejected. Password values are omitted from password-field validation errors, so the submitted value is not echoed. | I7: https://docs.google.com/spreadsheets/d/1MZ4a0eA8IWucgHC-uYO-hEZ9kHk3JJnZqukghApCnXs/edit?gid=0#gid=0&range=A7:J7 | J7: No defect.
A8: TC-UNIT-007 | B8: FR-03 User Account Management | C8: Username uniqueness is evaluated without case sensitivity. | D8: 1. Run the automated unit selector: uv run pytest backend/tests/test_tc_unit_users.py::TestUsernameUniqueness 2. Seed operator1, then request Operator1, OPERATOR1, and operator2. | E8: 1. 'Operator1' and 'OPERATOR1' are reported as taken. 2. 'operator2' is reported as available. | F8: 46261 | G8: Pass | H8: Pass. The exact duplicate operator1 was rejected. Operator1 and OPERATOR1 were also rejected as taken. operator2 was accepted. | I8: https://docs.google.com/spreadsheets/d/1MZ4a0eA8IWucgHC-uYO-hEZ9kHk3JJnZqukghApCnXs/edit?gid=0#gid=0&range=A8:J8 | J8: No defect.
A9: TC-UNIT-008 | B9: FR-04 Video Stream Ingestion | C9: A disabled camera is not started by the camera supervisor. | D9: 1. Run the automated unit selector: uv run pytest ai_engine/tests/test_supervisor.py::test_disabled_camera_is_not_started 2. Confirm the selected test passes and capture the run output. | E9: No stream is started for a disabled camera configuration. | F9: 46261 | G9: Pass | H9: Pass, full AI-engine fast suite: 127 passed, 7 skipped. | I9: https://docs.google.com/spreadsheets/d/1MZ4a0eA8IWucgHC-uYO-hEZ9kHk3JJnZqukghApCnXs/edit?gid=0#gid=0&range=A9:J9 | J9: No defect.
A10: TC-UNIT-009 | B10: FR-04 Video Stream Ingestion | C10: The camera reader keeps the newest frame until AI analysis consumes it. | D10: 1. Run the automated unit selector: uv run pytest ai_engine/tests/test_camera.py::test_latest_frame_wins_before_a_consumer_takes_it 2. Confirm the selected test passes and capture the run output. | E10: The latest frame is returned without an unbounded queue or stale-frame replay. | F10: 46261 | G10: Pass | H10: Pass, full AI-engine fast suite: 127 passed, 7 skipped. | I10: https://docs.google.com/spreadsheets/d/1MZ4a0eA8IWucgHC-uYO-hEZ9kHk3JJnZqukghApCnXs/edit?gid=0#gid=0&range=A10:J10 | J10: No defect.
A11: TC-UNIT-010 | B11: FR-04 Video Stream Ingestion | C11: The RTSP address builder combines stored VMS credentials with the camera channel. | D11: 1. Run the automated unit selector: uv run pytest backend/tests/test_tc_unit_incidents.py::TestRtspAddressBuilder 2. Build the address for channel 12 against a realistic Dahua DSS template and inspect the redacted form. | E11: 1. The address targets the configured VMS gateway, channel 12, and the 2K main stream parameter. 2. The credential portion is hidden in any logged or persisted representation. | F11: 46261 | G11: Pass | H11: Both acceptance conditions observed. Against the template rtsp://{dss_username}:{dss_password}@{dss_ip}:{dss_port}/cam/realmonitor?channel={channel_id}&subtype=0 the builder produced an address carrying 10.0.5.50:554, channel=12 and subtype=0, with subtype=1 absent, so the main stream is selected and no substream is. redact_text reduced the credential portion to ://***:***@ with neither the username nor the password surviving, while channel=12 and subtype=0 remained so the record stays diagnosable. Note: 2K is the encoder configuration on the main stream rather than a token in the URL, so what the address proves is main stream selection. 2 passed. | I11: https://docs.google.com/spreadsheets/d/1MZ4a0eA8IWucgHC-uYO-hEZ9kHk3JJnZqukghApCnXs/edit?gid=0#gid=0&range=A11:J11 | J11: No additional defect note was recorded in the tracker.
A12: TC-UNIT-011 | B12: FR-05 Automated Collision Detection | C12: Detector output excludes non-accident classes. | D12: 1. Run the automated unit selector: uv run pytest ai_engine/tests/test_detector.py::test_predict_batch_keeps_only_the_accident_class 2. Confirm the selected test passes and capture the run output. | E12: Only accident-class detections are passed to subsequent collision logic. | F12: 46261 | G12: Pass | H12: Pass, full AI-engine fast suite: 127 passed, 7 skipped. | I12: https://docs.google.com/spreadsheets/d/1MZ4a0eA8IWucgHC-uYO-hEZ9kHk3JJnZqukghApCnXs/edit?gid=0#gid=0&range=A12:J12 | J12: No defect.
A13: TC-UNIT-012 | B13: FR-05 Automated Collision Detection | C13: Sustained collision evidence emits an event after the required temporal window. | D13: 1. Run the automated unit selector: uv run pytest ai_engine/tests/test_accumulate.py::test_steady_detection_fires_after_roughly_two_seconds 2. Confirm the selected test passes and capture the run output. | E13: A stable detection fires only after approximately two seconds of accumulated evidence. | F13: 46261 | G13: Pass | H13: Pass, full AI-engine fast suite: 127 passed, 7 skipped. | I13: https://docs.google.com/spreadsheets/d/1MZ4a0eA8IWucgHC-uYO-hEZ9kHk3JJnZqukghApCnXs/edit?gid=0#gid=0&range=A13:J13 | J13: No defect.
... A69: TC-UNIT-068 | B69: NFR-22 Modular AI Upgrades | C69: A missing configured model fails closed rather than falling back. | D69: 1. Run the automated unit selector: uv run pytest ai_engine/tests/test_config.py::test_a_missing_model_is_fatal_rather_than_falling_back 2. Confirm the selected test passes and capture the run output. | E69: Configuration raises a clear error and never silently selects another model. | F69: 46261 | G69: Pass | H69: Pass, full AI-engine fast suite: 127 passed, 7 skipped. | I69: https://docs.google.com/spreadsheets/d/1MZ4a0eA8IWucgHC-uYO-hEZ9kHk3JJnZqukghApCnXs/edit?gid=0#gid=0&range=A69:J69 | J69: No defect.

Sheet Integration Testing
A1: Test ID | B1: Requirement / Objective | C1: Scenario | D1: Preconditions / Steps | E1: Expected Result / Acceptance | F1: Date Executed | G1: Result | H1: Actual Result / Notes | I1: Evidence Link | J1: Defect / Retest Note
A2: TC-INT-001 | B2: FR-04 Video Stream Ingestion | C2: The AI engine ingests and decodes a live RTSP stream published by the MediaMTX gateway. | D2: 1. Publish ai_engine/eval/clips/dekwatro.mp4 (2560x1440 h264, 2K) via MediaMTX as rtsp://localhost:8555/channel1. 2. Point camera 1 at that stream through RTSP_URL_TEMPLATE and start the AI engine. 3. Inspect the MediaMTX session log, the camera's reported connection_status, and the decoded frame products. | E2: 1. The engine completes the RTSP handshake and decodes frames as valid image arrays. 2. connection_status for the camera is reported as Connected on the following status check-in. 3. No local video file path is used as the frame source. | F2: 46261 | G2: Pass | H2: All three acceptance conditions observed. MediaMTX logged the engine creating an RTSP reading session on channel1 over TCP with 1 H264 track, so the handshake completed. Frames decoded to valid image arrays: the camera reported measured_fps 13.6 and inference_latency_ms 27.1, neither computable without decoded frames, and a detection from that stream produced an annotated JPEG that decodes to shape (1440, 2560, 3). connection_status was Connected on the following status check-in. The frame source was rtsp://localhost:8555/channel1 as reported by rtsp_url_redacted, an RTSP URL and not a local file path. | I2: https://docs.google.com/spreadsheets/d/1EQqHktDNbIqhYyCKQZHQ5_mb501YQG7j_nVoxZILCEs/edit?gid=0#gid=0&range=A2:J2 | J2: No additional defect note was recorded in the tracker.
A3: TC-INT-002 | B3: FR-06 Alert Generation and Snapshot Capture / FR-12 Incident Logging | C3: Engine-built alert message satisfies the server detection schema. | D3: 1. Run the automated integration selector: pytest selector: ai_engine/tests/test_contract.py::test_the_engines_payload_validates_against_the_backends_schema 2. Confirm the selected test passes and capture the run output. | E3: Server accepts the actual engine message shape, including all required fields. | F3: 46261 | G3: Pass | H3: 1 selected test passed in 1.24s. | I3: https://docs.google.com/spreadsheets/d/1EQqHktDNbIqhYyCKQZHQ5_mb501YQG7j_nVoxZILCEs/edit?gid=0#gid=0&range=A3:J3 | J3: No defect. final selected run passed.
A4: TC-INT-003 | B4: FR-06 Alert Generation and Snapshot Capture | C4: A webhook-created incident reaches a connected operator through the real-time channel. | D4: 1. Run the automated integration selector: pytest selector: backend/tests/test_websocket.py::test_internal_alert_broadcasts_to_websocket_client 2. Confirm the selected test passes and capture the run output. | E4: Connected client receives versioned NEW_DETECTION followed by CAMERA_STATUS_UPDATE with the correct data. | F4: 46261 | G4: Pass | H4: 4 selected tests passed in 0.80s. | I4: https://docs.google.com/spreadsheets/d/1EQqHktDNbIqhYyCKQZHQ5_mb501YQG7j_nVoxZILCEs/edit?gid=0#gid=0&range=A4:J4 | J4: No defect. final selected run passed.
A5: TC-INT-004 | B5: FR-06 Alert Generation and Snapshot Capture | C5: Frontend runtime accepts a server NEW_DETECTION WebSocket envelope. | D5: 1. Run the automated integration selector: Vitest selector: frontend/src/api/events.test.ts -t "accepts a NEW_DETECTION envelope emitted by the backend" 2. Confirm the selected test passes and capture the run output. | E5: The frontend envelope parser and incident validator accept the server alert message. | F5: 46261 | G5: Pass | H5: 11 tests in 1 file passed in 1.44s. | I5: https://docs.google.com/spreadsheets/d/1EQqHktDNbIqhYyCKQZHQ5_mb501YQG7j_nVoxZILCEs/edit?gid=0#gid=0&range=A5:J5 | J5: Test-only contract coverage added. Mutation check failed when either event type was removed. production code restored and final file run passed.
A6: TC-INT-005 | B6: FR-06 Alert Generation and Snapshot Capture | C6: A snapshot written by the AI engine is retrievable through the authenticated server route. | D6: 1. Let the engine detect on the live 2K stream and persist its annotated snapshot. 2. Read snapshot_key from the created incident (log_id 20). 3. GET /api/alerts/20/snapshot as an authenticated Operator, then again with no session. 4. Inspect the alert detail response for any filesystem path. | E6: 1. The authenticated request returns the JPEG image with the bounding box drawn. 2. The unauthenticated request is rejected and no image bytes are returned. 3. The stored key never appears as a filesystem path in the API response. | F6: 46261 | G6: Pass | H6: All three acceptance conditions observed. The authenticated request returned 200 image/jpeg, 1,040,842 bytes, magic ffd8ff, decoding to (1440, 2560, 3), and the image visibly carries the red bounding box drawn around the collision. The unauthenticated request was rejected 401 AUTH_REQUIRED returning 68 bytes of JSON and no image bytes. The stored key 2026/09/14/camera_1/a75b8e65-... never appears in the API response: the detail body exposes only snapshot_url /api/alerts/20/snapshot, with no .jpg reference, no drive-letter or absolute path, and no snapshots directory name. Setup note: an earlier attempt returned 404 because AI_SNAPSHOT_ROOT and the backend SNAPSHOT_ROOT had been pointed at different directories in the harness. That is the mismatch ai_engine/config.py:29 warns about, not a product fault. Re-run with the roots aligned. | I6: https://docs.google.com/spreadsheets/d/1EQqHktDNbIqhYyCKQZHQ5_mb501YQG7j_nVoxZILCEs/edit?gid=0#gid=0&range=A6:J6 | J6: No additional defect note was recorded in the tracker.
A7: TC-INT-006 | B7: FR-10 False Positive Handling | C7: A dismissal propagates a cooldown that the AI engine honours before resuming detection. | D7: 1. Dismiss the open incident on camera 1 through the API and read cooldown_until. 2. Keep the engine running and the detectable 2K stream replaying throughout the cooldown window. 3. Poll the camera every 15 seconds across the window and past expiry. 4. Query detection_log for incidents created during and after the window. | E7: 1. The status check-in returns Paused with the cooldown reason and the cooldown_until timestamp. 2. No new incident is created for camera A while the cooldown is unexpired. 3. After expiry the engine returns to Active and the replayed content produces a new incident. | F7: 46261 | G7: Pass | H7: All three acceptance conditions observed. On dismissal the camera reported desired_ai_state Paused with desired_state_reason cooldown and cooldown_until 2026-09-14T08:38:36.810754Z. Across the cooldown window the engine acknowledged the pause (ai_status Paused at t+30s and t+45s) and created no new incident for camera 1, confirmed by a direct query returning zero rows between the dismissal and expiry. After expiry the camera resumed and the replayed content produced a new incident, log_id 20, detected_at 08:38:38.358769, which is 1.5 seconds after cooldown_until. Exactly one new incident resulted. | I7: https://docs.google.com/spreadsheets/d/1EQqHktDNbIqhYyCKQZHQ5_mb501YQG7j_nVoxZILCEs/edit?gid=0#gid=0&range=A7:J7 | J7: No additional defect note was recorded in the tracker.
A8: TC-INT-007 | B8: FR-11 True Positive Handling | C8: AI self-reporting Active cannot clear the server's HITL incident pause. | D8: 1. Run the automated integration selector: pytest selector: backend/tests/test_internal.py::TestHeartbeat::test_self_reported_active_does_not_override_the_hitl_pause 2. Confirm the selected test passes and capture the run output. | E8: Observed AI state is recorded, but the returned desired state remains Paused while the incident is open. | F8: 46261 | G8: Pass | H8: 4 selected tests passed in 1.03s. | I8: https://docs.google.com/spreadsheets/d/1EQqHktDNbIqhYyCKQZHQ5_mb501YQG7j_nVoxZILCEs/edit?gid=0#gid=0&range=A8:J8 | J8: No defect. final selected run passed.
A9: TC-INT-008 | B9: FR-11 True Positive Handling | C9: Clearing an incident resumes the camera and notifies operators of both state changes. | D9: 1. Run the automated integration selector: pytest selector: backend/tests/test_websocket.py::test_clear_alert_broadcasts_camera_status_update_over_websocket 2. Confirm the selected test passes and capture the run output. | E9: Client receives CAMERA_STATUS_UPDATE then ALERT_STATUS_UPDATE showing the Cleared incident. | F9: 46261 | G9: Pass | H9: Pass, P28 targeted rerun: 1 selected test passed. | I9: https://docs.google.com/spreadsheets/d/1EQqHktDNbIqhYyCKQZHQ5_mb501YQG7j_nVoxZILCEs/edit?gid=0#gid=0&range=A9:J9 | J9: No defect. final selected run passed.
A10: TC-INT-009 | B10: FR-12 Incident Logging | C10: A retry of one AI source event preserves a single incident row. | D10: 1. Run the automated integration selector: pytest selector: backend/tests/test_internal.py::TestReceiveAiAlertV2::test_v2_idempotent_retry_returns_200_same_row 2. Confirm the selected test passes and capture the run output. | E10: First webhook call returns 201. retry returns 200 with the same log ID and no duplicate row. | F10: 46261 | G10: Pass | H10: 4 selected tests passed in 1.03s. | I10: https://docs.google.com/spreadsheets/d/1EQqHktDNbIqhYyCKQZHQ5_mb501YQG7j_nVoxZILCEs/edit?gid=0#gid=0&range=A10:J10 | J10: No defect. final selected run passed.
A11: TC-INT-010 | B11: FR-14 Camera Configuration Management | C11: A changed status check-in status is sent out to every connected operator. | D11: 1. Run the automated integration selector: pytest selector: backend/tests/test_websocket.py::test_heartbeat_status_change_broadcasts_to_all_connected_websocket_clients 2. Confirm the selected test passes and capture the run output. | E11: Each connected client receives the same versioned CAMERA_STATUS_UPDATE message. | F11: 46261 | G11: Pass | H11: 4 selected tests passed in 0.80s. | I11: https://docs.google.com/spreadsheets/d/1EQqHktDNbIqhYyCKQZHQ5_mb501YQG7j_nVoxZILCEs/edit?gid=0#gid=0&range=A11:J11 | J11: No defect. final selected run passed.
A12: TC-INT-011 | B12: FR-14 Camera Configuration Management | C12: Frontend runtime accepts a server CAMERA_STATUS_UPDATE WebSocket envelope. | D12: 1. Run the automated integration selector: Vitest selector: frontend/src/api/events.test.ts -t "accepts a CAMERA_STATUS_UPDATE envelope emitted by the backend" 2. Confirm the selected test passes and capture the run output. | E12: The frontend envelope parser and camera validator accept the server camera-status message. | F12: 46261 | G12: Pass | H12: 11 tests in 1 file passed in 1.44s. | I12: https://docs.google.com/spreadsheets/d/1EQqHktDNbIqhYyCKQZHQ5_mb501YQG7j_nVoxZILCEs/edit?gid=0#gid=0&range=A12:J12 | J12: Test-only contract coverage added. Mutation check failed when either event type was removed. production code restored and final file run passed.
A13: TC-INT-012 | B13: FR-14 Camera Configuration Management | C13: A camera created through the server is started by the AI engine on the next status check-in. | D13: 1. With the engine already running, POST /api/cameras/ to create a camera on channel 8, which MediaMTX publishes. 2. Wait for status check-in exchanges without restarting the engine. 3. Inspect the camera record, the MediaMTX reader count, and the engine process start time. | E13: 1. The status check-in response carries the new camera with desired_ai_state Active and the incremented config_version. 2. The engine starts a worker for that camera without restart. 3. applied_config_version on the camera record matches the server config_version. | F13: 46261 | G13: Pass | H13: All three acceptance conditions observed. The created camera (camera_id 9, channel 8) carried desired_ai_state Active with config_version 1. The engine started a worker for it without any restart: the engine processes 23264 and 25808 had started at 16:37:52 and were still the same processes when the camera was created around 16:52, and MediaMTX reported channel8 with exactly 1 reader. The camera reached connection_status Connected and ai_status Active within 8 seconds and reported measured_fps rising to 13.2. applied_config_version 1 matched the server config_version 1. | I13: https://docs.google.com/spreadsheets/d/1EQqHktDNbIqhYyCKQZHQ5_mb501YQG7j_nVoxZILCEs/edit?gid=0#gid=0&range=A13:J13 | J13: No additional defect note was recorded in the tracker.
... A24: TC-INT-023 | B24: NFR-22 Modular AI Upgrades | C24: A compatible replacement collision-detection model can be deployed through the existing AI integration boundary without source-code changes. | D24: 1. Establish a baseline with the currently deployed model using the authorized main RTSP feed; record its artifact/configuration, source revision, input/output contract, and class mapping. 2. Prepare a second compatible model, potentially newer or better, that satisfies the existing input, preprocessing, output, and event-contract requirements. 3. Change only the model artifact reference/configuration and perform the normal model reload or service restart; do not modify application source code, backend logic, dashboard logic, or the test harness. 4. Run the same main-feed path and verify model loading, inference, detection output, event creation, and downstream consumption. 5. Restore the original model by reversing the artifact/configuration change and verify that the baseline path still works. | E24: 1. The replacement model loads and runs through the same integration boundary. 2. Swapping models requires no source-code, backend, dashboard, or event-contract changes; only the approved model artifact/configuration changes. 3. Required detection and event outputs remain compatible with downstream components. 4. The original model can be restored through the same mechanism. 5. Any accuracy or performance difference is recorded separately; this case proves replaceability, not that the replacement is better or produces identical per-clip decisions. | F24: 46261 | G24: Pass | H24: Pass (qualified artifact-level check). The current .env remained AI_MODEL_PATH=ai_engine/epoch50.engine; an isolated AI_MODEL_PATH swap to ai_engine/epoch50.onnx resolved and loaded through config.resolve_model_path()/AccidentDetector with no source-code change. Fresh same-clip runs on the NVIDIA GeForce RTX 3050 Ti Laptop GPU: both artifacts produced 4 events on car-motor.mp4 (hit=true) and 0 events on airbase.mp4 (hit=false); both emitted the same event fields age_s, box, peak_conf, score, and t. The original .env remained unchanged and git status was clean. ONNX emitted a CUDAExecutionProvider plugin warning but exited 0. Limitation: ONNX is exported from the same epoch50 weights; no separately trained/better model or live RTSP/backend/dashboard session was available, so this is artifact-level NFR-22 evidence and should be repeated with a separately trained compatible candidate. | I24: https://docs.google.com/spreadsheets/d/1EQqHktDNbIqhYyCKQZHQ5_mb501YQG7j_nVoxZILCEs/edit?gid=0#gid=0&range=A24:J24 | J24: No additional defect note was recorded in the tracker.

Sheet System E2E Testing
A1: Test ID | B1: Requirement / Objective | C1: Scenario | D1: Preconditions / Steps | E1: Expected Result / Acceptance | F1: Date Executed | G1: Result | H1: Actual Result / Notes | I1: Evidence Link | J1: Defect / Retest Note
A2: TC-SYS-001 | B2: FR-01 User Authentication / FR-02 Role-Based Access Control (RBAC) | C2: Operator and Administrator authenticate through the deployed browser and receive role-appropriate access. | D2: Entry gate: build d066aaf, all six enabled streams Connected, single-node deployment. 1. Sign in at http://localhost:5174 as Operator dsahagun. 2. Read the rendered navigation and search it for each Administrator destination. 3. Sign out, sign in as Administrator rmanalo, and read the navigation again. 4. Query the audit trail for both sign-in events. | E2: 1. Both valid accounts authenticate successfully against the deployed build. 2. The Operator session exposes no Administrator-only destination. 3. The Administrator session exposes every Operator destination plus User Management, AI Performance, Audit Log, and Maintenance. 4. Both sign-in events appear in the audit trail. | F2: 46262 | G2: Pass | H2: All four acceptance conditions observed. Both accounts authenticated against the running build. The Operator session rendered OPERATIONS (Dashboard, Cameras, Detections), MONITORING (System Health), ACCOUNT (Profile) and Help Center only, and an accessibility-tree search returned no match for User Management, AI Performance, Audit Log or Maintenance, so they are absent from the rendered output rather than hidden by style. The Administrator session rendered every Operator destination plus an ADMINISTRATION group containing Users, Audit Log, Maintenance and AI Performance. Both sign-ins appear in the audit trail as LOGIN_SUCCESS with actor, role, session target_ref, result success and source_ip 127.0.0.1 (audit_id 47 and 48 for rmanalo, and the corresponding Operator row). | I2: https://docs.google.com/spreadsheets/d/127sqg1pWCKvnr1KYa2ctscpMyJDphAcq6-xflAvkjJ0/edit?gid=0#gid=0&range=A2:J2 | J2: No additional defect note was recorded in the tracker.
A3: TC-SYS-002 | B3: FR-03 User Account Management / FR-20 Activity Audit Trail | C3: An Administrator completes the full account lifecycle for an Operator. | D3: 1. Sign in as Administrator rmanalo. 2. POST /api/users/ to create Operator tclifecycle, then sign that account in from a separate cookie jar standing in for a second browser. 3. Confirm the new account's role and that Administrator-only routes are refused to it. 4. Edit the account, then reset its password as Administrator and re-check the target's active session. 5. Deactivate, attempt sign-in, filter the directory to deactivated accounts, restore, and sign in again. | E3: 1. The new account authenticates and receives Operator permissions only. 2. Edits and the password change take effect, and the password change ends the target user's active sessions. 3. The deactivated account is refused with the generic sign-in failure. 4. The restored account authenticates again and its earlier audit history is still attributed to it. 5. Every account action is recorded in the audit trail. | F3: 46262 | G3: Pass | H3: All five acceptance conditions observed. The new account (user_id 9) authenticated and carried role Operator only: /api/users/me returned Operator, while GET /api/users/, /api/audit-logs/ and /api/system/backups were each refused 403. Edits took effect (first_name updated, 200) and the Administrator password reset returned 204. Session invalidation was verified cleanly on a fresh login: the target's session returned 200 immediately before the reset and 401 immediately after, and the old password was then refused 401 while the new one authenticated 200. The deactivated account was refused with the generic sign-in failure, 401 'Incorrect username or password.' with code AUTH_INVALID_CREDENTIALS, byte-identical to a wrong-password response, so a deactivated account cannot be enumerated. The deactivated directory filter returned the account, restoration set is_active true, and it authenticated again on the same user_id 9, so its earlier audit history stays attributed to it. Every account action was audited: USER_CREATE (67), USER_UPDATE (69, 70, 73), USER_DISABLE (71), USER_ENABLE (74) and USER_PASSWORD_RESET (76, 80), all by rmanalo with result success. | I3: https://docs.google.com/spreadsheets/d/127sqg1pWCKvnr1KYa2ctscpMyJDphAcq6-xflAvkjJ0/edit?gid=0#gid=0&range=A3:J3 | J3: No additional defect note was recorded in the tracker.
A4: TC-SYS-003 | B4: FR-03 User Account Management / NFR-19 Session Security | C4: An Operator updates their own profile and password through self-service. | D4: 1. Sign in as an Operator and open the profile page. 2. Edit the first name through the Edit Personal Information dialog and save, watching the displayed identity. 3. Change the password over /api/users/me/password using the correct current password. 4. Attempt a second change with an incorrect current password. 5. Re-authenticate with the new password. | E4: 1. Profile edits persist and the displayed identity updates without a reload. 2. The valid password change succeeds and the prior session is no longer usable. 3. The invalid attempt is refused with a field-level error and the stored password is unchanged. 4. The new password authenticates successfully. | F4: 46262 | G4: Pass | H4: All four acceptance conditions observed. Profile edits persisted and the displayed identity updated in place without a page reload: saving the dialog changed the profile header, the First Name field and the sidebar account label together, and username and last name edits persisted through the API as well. The valid password change returned 204 and the prior session was no longer usable, returning 401 on the very next request. The invalid attempt was refused with a field-targeted error, 400 'Current password is incorrect.' with code PRECONDITION_FAILED, and the stored password was unchanged: the original password still authenticated 200 while the attempted replacement was refused 401. Note the response names the offending field in its message rather than returning a structured per-field errors array, which is null on this endpoint. The new password authenticated successfully, 200. | I4: https://docs.google.com/spreadsheets/d/127sqg1pWCKvnr1KYa2ctscpMyJDphAcq6-xflAvkjJ0/edit?gid=0#gid=0&range=A4:J4 | J4: No additional defect note was recorded in the tracker.
A5: TC-SYS-004 | B5: FR-04 Video Stream Ingestion / FR-05 Automated Collision Detection / FR-06 Alert Generation and Snapshot Capture / FR-09 Human-in-the-Loop (HITL) Verification Workflow / FR-11 True Positive Handling / FR-12 Incident Logging | C5: A live collision feed becomes a confirmed and then cleared incident in the operator browser. | D5: Entry gate: all seven configured streams ingesting, channel1 replaying the 2K dekwatro.mp4 collision clip on camera 1 (Ayala Highway Cam). 1. Sign in as Operator dsahagun and let the replayed collision reach the live engine. 2. Observe the alert modal, the alarm, and the annotated snapshot. 3. Select Confirm Accident and inspect the incident and camera state. 4. Open the incident from the Ongoing incidents tray and select Cleared. 5. Query detection_log, camera and audit_log for the full lifecycle. | E5: 1. Exactly one incident is created with a snapshot and Unverified status. 2. Confirm records Ongoing with the verifying operator and time, and the camera stays paused. 3. Cleared records the closing operator and time, and the camera returns to Active. 4. The complete lifecycle is visible in the incident history and the audit trail. | F5: 46262 | G5: Pass | H5: All four acceptance conditions observed on a genuine live detection. Exactly one incident was created, log_id 19, Unverified, confidence 0.847, with a real annotated snapshot: the blocking modal rendered the 2560x1440 night frame with the red bounding box drawn around the collision, alongside camera name Ayala Highway Cam, the detection timestamp and the AI confidence of 84.7%. Confirm recorded Ongoing with verified_by_id 2 (dsahagun) and verified_at 09:51:23.933178, and the camera stayed Paused with desired_state_reason incident. Cleared recorded closed_by_id 2 and closed_at 09:52:41.992576, and the camera returned to desired_ai_state Active with ai_status Active, reason cleared to None and no cooldown. The complete lifecycle is present in the audit trail as four rows scoped to incident 19: ALERT_SNOOZE (audit_id 61), ALERT_SNOOZE (62), ALERT_CONFIRM (63) and ALERT_CLEAR (64), all attributed to dsahagun. | I5: https://docs.google.com/spreadsheets/d/127sqg1pWCKvnr1KYa2ctscpMyJDphAcq6-xflAvkjJ0/edit?gid=0#gid=0&range=A5:J5 | J5: No additional defect note was recorded in the tracker.
A6: TC-SYS-005 | B6: FR-06 Alert Generation and Snapshot Capture / FR-09 Human-in-the-Loop (HITL) Verification Workflow / FR-10 False Positive Handling / FR-12 Incident Logging | C6: A controlled false-positive alert is dismissed and the affected camera completes its cooldown before monitoring resumes. | D6: Entry gate: all configured streams ingesting, camera 1 replaying the detectable collision clip. 1. Sign in as Operator and wait for a live alert (log_id 20). 2. Observe the alert and its snapshot, then select Dismiss Accident. 3. Inspect the incident record and the camera cooldown state. 4. Observe other cameras throughout, and wait out the cooldown. | E6: 1. The alert leaves the active queue immediately on Dismiss. 2. The incident record reads Dismissed and names the acting user. 3. Only the affected camera pauses, for 60 seconds, and other cameras keep detecting. 4. The camera resumes Active detection after the cooldown with no duplicate alert for the same stimulus. | F6: 46262 | G6: Pass | H6: All four acceptance conditions observed on a live detection. The alert left the active queue immediately on Dismiss and the blocking modal closed. The incident record reads Dismissed and names the acting user: verified_by_id 2 (dsahagun) with verified_at 09:54:14.771488. Note on the schema, checked against app/services/incidents.py: any transition out of Unverified records the actor in verified_by_id rather than closed_by_id, so closed_by_id is null on this false-positive path by design. The actor is additionally in the audit trail as audit_id 65 ALERT_DISMISS, dsahagun, Operator, success. Only the affected camera paused, with desired_state_reason cooldown and a cooldown_until exactly 60.0 seconds after the dismissal instant, while cameras 2 and 5 remained ai_status Active throughout. After expiry camera 1 returned to desired_ai_state Active with reason None and cooldown_until cleared, and no duplicate incident was created for the same stimulus during or immediately after the cooldown. | I6: https://docs.google.com/spreadsheets/d/127sqg1pWCKvnr1KYa2ctscpMyJDphAcq6-xflAvkjJ0/edit?gid=0#gid=0&range=A6:J6 | J6: No additional defect note was recorded in the tracker.
A7: TC-SYS-006 | B7: FR-07 Audible Alert Timeout and Escalation / FR-09 Human-in-the-Loop (HITL) Verification Workflow | C7: The snooze window expires and re-alarms before the operator reaches a decision. | D7: 1. Set the operator's snooze duration to its minimum of 15 seconds. 2. On a live alert (log_id 19), select Snooze alarm and read snoozed_at and snoozed_until. 3. Instrument HTMLMediaElement.play() in the page, take no further action, and wait for the window to elapse. 4. Snooze a second time and confirm a fresh countdown. 5. Select Confirm Accident and observe whether further re-alarms occur. | E7: 1. Snooze mutes the alarm for that alert only and starts the countdown. 2. The alarm re-triggers for that alert when the window expires and the incident is still Unverified. 3. A second snooze starts a fresh countdown. 4. Confirming inside the window suppresses further re-alarms and records the snoozing user and time on the incident. | F7: 46262 | G7: Pass | H7: All four acceptance conditions observed. Snooze muted the alarm for that alert alone and started the countdown: snoozed_at 09:47:07.563581 with snoozed_until 09:47:22.563581, a window of exactly 15.0 seconds, recorded against snoozed_by_id 2, with the incident remaining Unverified. The alarm re-triggered on expiry with the incident still Unverified: an instrumented play() call fired at 09:47:22.579Z, within 16 ms of the recorded expiry. A second snooze started a fresh countdown, snoozed_at moving to 09:48:42.053260 with snoozed_until 09:48:57.053260, again exactly 15.0 seconds, and the alarm re-triggered again at 09:48:57.066Z, within 13 ms. Confirming suppressed further re-alarms: no play() call was recorded in the 30 seconds after the confirm at 09:51:23, and the snoozing user and times are preserved in the audit trail as audit_id 61 and 62 ALERT_SNOOZE by dsahagun, each carrying its snoozed_until. Note that the incident row's own snooze fields are cleared on transition out of Unverified, so the durable record of who snoozed and when is the audit trail. See DEF-006 for the alarm sound and volume used on these re-alarms, which does not affect this case's acceptance conditions. | I7: https://docs.google.com/spreadsheets/d/127sqg1pWCKvnr1KYa2ctscpMyJDphAcq6-xflAvkjJ0/edit?gid=0#gid=0&range=A7:J7 | J7: DEF-006
A8: TC-SYS-007 | B8: FR-08 Alarm Configuration Module / NFR-11 Alert Distinctiveness | C8: Alarm personalisation persists across sessions and governs the next alert. | D8: 1. Sign in as Operator and open Profile, Alarm Settings. 2. Select a different alarm sound (Buzzer), adjust the volume, and set the snooze duration inside the 15 to 60 second range. 3. Observe the save status indicator without pressing a separate save control. 4. Re-authenticate in a fresh session and confirm the settings are restored. 5. Let a live alert arrive and instrument HTMLMediaElement.play() to capture the sound file and volume actually used. | E8: 1. The preview plays the selected sound at the configured volume. 2. Settings persist automatically and the status indicator reports the saved state. 3. The same settings are restored after re-authentication. 4. The next alert uses the selected sound, volume, and snooze duration. | F8: 46262 | G8: Pass | H8: Retest passed. Four focused frontend test files passed all 32 tests. Live browser verification persisted the selected sound and volume across a fresh session; the next alert invoked digital_alarm.mp3 at volume 0.35 with loop=true. Cleanup restored the default settings. | I8: var/test-evidence/retest-sys007-20260916.json | J8: Prior DEF-006 behavior was not reproduced; the required persistence and live playback behavior was observed in this retest.
A9: TC-SYS-008 | B9: FR-09 Human-in-the-Loop (HITL) Verification Workflow / Objective 2 Real-time alert dashboard | C9: Two concurrent operator dashboards converge on a single incident decision. | D9: 1. Sign in as Operator tcselfserve in the browser as workstation A. 2. Sign in as a different Operator (ealonzo) from an independent session and open the same /ws/alerts channel the dashboard uses, with the session cookie attached on the handshake, as workstation B. 3. Let a live collision alert arrive while both are connected. 4. Confirm the alert on workstation A and observe workstation B without refreshing it. 5. Attempt a second, conflicting verification from workstation B. | E9: 1. Both workstations receive the alert and alarm. 2. After the decision on A, workstation B removes the alert from its active queue and shows the incident as Ongoing. 3. Exactly one incident record exists, attributed to the operator who acted. 4. Workstation B cannot record a second conflicting verification. | F9: 46262 | G9: Pass | H9: All four acceptance conditions observed with two genuinely independent operator sessions. Both workstations received the alert. Workstation B connected at 10:20:06.512Z, before the detection, and received NEW_DETECTION for log_id 23 at 10:21:09.921Z carrying status Unverified, camera 1 and confidence 0.841, while workstation A raised the same alert as its blocking modal. This was a live broadcast, not a reconnect replay. After the decision on A, workstation B saw the incident become Ongoing without any refresh: it received ALERT_STATUS_UPDATE for log_id 23 with status Ongoing at 10:21:25.585Z, 24 milliseconds after A's confirm was committed at 10:21:25.561576. Exactly one incident record exists for that detection, log_id 23, attributed to verified_by_id 9 (tcselfserve), the operator who acted, and not to B. Workstation B could not record a conflicting verification: its confirm was refused 409 CONFLICT_STATE with 'This incident was already handled by another operator.' and a body naming current_status Ongoing and handled_action ALERT_CONFIRM. Workstation B captured 249 frames in total across the window, comprising CONNECTION_READY, NEW_DETECTION, ALERT_STATUS_UPDATE and 246 CAMERA_STATUS_UPDATE frames. | I9: https://docs.google.com/spreadsheets/d/127sqg1pWCKvnr1KYa2ctscpMyJDphAcq6-xflAvkjJ0/edit?gid=0#gid=0&range=A9:J9 | J9: No additional defect note was recorded in the tracker.
A10: TC-SYS-009 | B10: FR-09 Human-in-the-Loop (HITL) Verification Workflow / NFR-10 Workflow Efficiency | C10: The alert decision path is reachable without intermediate navigation. | D10: 1. Let a live alert be presented on the deployed build. 2. Read the alert dialog's full control inventory from the accessibility tree and count the interactions needed to reach each recorded decision. 3. Exercise Snooze, then reach a Confirm decision, counting actions. 4. Record what information is visible without leaving the alert. | E10: 1. Confirm and Dismiss are each reachable from the presented alert in a single action, with no intermediate navigation. 2. Snooze adds exactly one action and does not reset or lengthen the decision path. 3. The snapshot, camera, timestamp, and confidence score are visible without leaving the alert. 4. The observed interaction counts are recorded for comparison with the NFR-09 timing result. | F10: 46262 | G10: Pass | H10: All four acceptance conditions observed. The presented alert is an alertdialog whose entire control inventory is Zoom snapshot, Snooze alarm, Dismiss Accident and Confirm Accident, so Confirm and Dismiss are each reachable in a single action from the alert with no intermediate navigation. A single click on Dismiss Accident removed the alert and advanced the queue from 'Alert 1 of 3' to 'Alert 1 of 2', and a single click on Confirm Accident moved log_id 19 to Ongoing. Snooze adds exactly one action and does not lengthen the decision path: it is one click in the same dialog, and after snoozing, Confirm and Dismiss remained directly available in that same dialog, with the subsequent Confirm still a single click. The snapshot with its bounding box, the camera name, the detection timestamp and the AI confidence score were all visible inside the alert without leaving it. Interaction counts recorded for comparison with the NFR-09 timing result: Confirm 1 action, Dismiss 1 action, Snooze then decide 2 actions. Also observed: the alert dialog is genuinely modal. Clicks on Log Out and on sidebar destinations were not actioned while an alert was pending, which is the intended human-in-the-loop blocking behaviour. | I10: https://docs.google.com/spreadsheets/d/127sqg1pWCKvnr1KYa2ctscpMyJDphAcq6-xflAvkjJ0/edit?gid=0#gid=0&range=A10:J10 | J10: No additional defect note was recorded in the tracker.
A11: TC-SYS-010 | B11: FR-11 True Positive Handling / FR-12 Incident Logging | C11: An operator corrects a mistaken confirmation through terminal dismissal. | D11: 1. Confirm a live alert so the incident becomes Ongoing (log_id 21). 2. Open the ongoing incident from the Ongoing incidents tray. 3. Select Dismiss Accident to correct the earlier decision. 4. Inspect the incident record, the camera state and the audit trail. | E11: 1. The incident moves from Ongoing to Dismissed and stops appearing as active. 2. Both the original verification and the correcting closure are recorded with their users and times. 3. AI detection resumes on the affected camera. 4. Both actions are present in the audit trail. | F11: 46262 | G11: Pass | H11: All four acceptance conditions observed. The incident moved from Ongoing to Dismissed and left the active set. Both decisions are recorded with their users and times: verified_by_id 9 with verified_at 10:16:49.449305 from the original confirmation, and closed_by_id 9 with closed_at 10:17:18.296552 from the correcting closure. AI detection resumed on the affected camera, and the proof is direct rather than inferred: cooldown_until stayed null, consistent with the documented rule that an operator correction resumes immediately rather than entering the 60 second false-positive cooldown, and a fresh detection on that same camera was created at 10:17:20.718594, two seconds after the correction, which is only possible if analysis had resumed. Both actions appear in the audit trail with distinct action names: ALERT_CONFIRM (audit_id 88) and ALERT_CORRECTION (89), both by tcselfserve with result success, so a correction is distinguishable from an ordinary dismissal in the trail. | I11: https://docs.google.com/spreadsheets/d/127sqg1pWCKvnr1KYa2ctscpMyJDphAcq6-xflAvkjJ0/edit?gid=0#gid=0&range=A11:J11 | J11: No additional defect note was recorded in the tracker.
A12: TC-SYS-011 | B12: FR-12 Incident Logging / FR-13 Historical Logs Search and Filtering / FR-18 Report Generation and Data Export / FR-20 Activity Audit Trail | C12: An operator filters completed incident history and exports one normal-sized report from the deployed browser. | D12: 1. Sign in and open Detections, Logs tab. 2. Apply a combined date, camera and handler filter (camera_id 1, user_id 2, 2026-09-01 to 2026-09-30 Asia/Manila). 3. Compare the returned records against a direct sqlite3 query. 4. Export the same filtered scope as CSV and compare its rows. 5. Inspect the export audit entry. Timing deliberately not recorded. | E12: 1. Filtered history shows only records matching every applied filter. 2. The export opens cleanly and its rows match the displayed filter scope exactly. 3. The export action is recorded in the audit trail with the applied filters. 4. Performance timing for exports is reported separately under Performance and Load Testing. | F12: 46262 | G12: Pass | H12: All four acceptance conditions observed. The combined filter returned exactly 2 records, log_id 1 and 2, both on camera 1 and both handled by user 2 inside the date range, matching the independent SQL result [2, 1] exactly. The CSV export opened cleanly and contained exactly those same two rows with their full lifecycle fields (Dismissed 97.0% and Cleared 93.0%, both Ayala Highway Cam, handler Daniel Luis Sahagun). The export was recorded as audit_id 53 REPORT_EXPORT carrying the applied filters start_date, end_date, camera_id [1], user_id [2] and row_count 2. No timing was recorded in this case, as instructed. | I12: https://docs.google.com/spreadsheets/d/127sqg1pWCKvnr1KYa2ctscpMyJDphAcq6-xflAvkjJ0/edit?gid=0#gid=0&range=A12:J12 | J12: No additional defect note was recorded in the tracker.
A13: TC-SYS-012 | B13: FR-12 Incident Logging / FR-13 Historical Logs Search and Filtering | C13: An operator reviews the full lifecycle of a historical incident. | D13: 1. Open Detections and locate a terminal incident in the log. 2. Search by accident number exactly as displayed, then open the record with its view action. 3. Inspect the snapshot, telemetry and lifecycle fields in the detail modal. 4. Read the modal's full control inventory to check for any edit control. | E13: 1. The modal shows the snapshot with its bounding box, the detection time, camera, and confidence score. 2. Snooze, verification, and closure actions are shown with the responsible personnel and exact times. 3. The record is read-only and offers no edit control for a terminal incident. | F13: 46262 | G13: Pass | H13: All three acceptance conditions observed. The detail modal for ACC-000021, badged DISMISSED, showed the real annotated snapshot with its red bounding box drawn on the 2K frame, the detection time 09/14/2026 17:55:24, the camera name Ayala Highway Cam and the AI confidence score 74.3%. The verification and closure actions were shown with the responsible personnel and exact times: Verified By Selfie Served at 18:16:49 and Closed By Selfie Served at 18:17:18. This particular incident carried no snooze, so no snooze row was applicable; snooze capture is evidenced separately under TC-SYS-006. The record is read-only for a terminal incident: the dialog's entire interactive inventory is 'Close incident details' and 'Zoom in on Accident snapshot', with no Confirm, Dismiss, Clear or edit control present, in contrast to the same modal opened on an Ongoing incident which does offer Dismiss Accident. Defect found while performing step 2, which does not affect these acceptance conditions: searching the accident number in the exact form the interface displays it returns no results. See DEF-007. | I13: https://docs.google.com/spreadsheets/d/127sqg1pWCKvnr1KYa2ctscpMyJDphAcq6-xflAvkjJ0/edit?gid=0#gid=0&range=A13:J13 | J13: DEF-007
... A22: TC-SYS-021 | B22: NFR-19 Session Security | C22: Logging out ends the session and stops live alert delivery. | D22: 1. Sign in as an Operator and open the live /ws/alerts channel used by the dashboard, confirming delivery. 2. Log out through the API (the same call the interface's Log Out control issues) and through the browser's Log Out control directly. 3. Attempt to navigate back to a protected page using browser history. 4. Replay the pre-logout session cookie and observe the previously open channel. | E22: 1. The session ends, the authentication cookie is cleared, and the browser returns to the login page. 2. The back navigation does not restore access and redirects to login. 3. No alert message reaches the closed client. 4. The logout is recorded in the audit trail. | F22: 46262 | G22: Pass | H22: All four acceptance conditions observed. The session ended, the cookie was rejected on the very next request (401), and in the browser the Log Out control returned to /login. Browser back navigation from a protected page after logout landed on /login rather than restoring the prior view; navigating directly to a protected route (/user/health) after logout also redirected to /login. No alert message reached the closed client: the server actively closed the previously open WebSocket with close code 4009, reason 'logout', rather than leaving it open and simply withholding frames, and 0 further frames arrived on it afterward. The logout is recorded in the audit trail (LOGOUT, result success, target_type session) with the session's revocation_reason set to 'logout'. | I22: https://docs.google.com/spreadsheets/d/127sqg1pWCKvnr1KYa2ctscpMyJDphAcq6-xflAvkjJ0/edit?gid=0#gid=0&range=A22:J22 | J22: No additional defect note was recorded in the tracker.

Sheet AI Model Validation
A1: Test ID | B1: Requirement / Objective | C1: Scenario | D1: Preconditions / Steps | E1: Expected Result / Acceptance | F1: Date Executed | G1: Result | H1: Actual Result / Notes | I1: Evidence Link | J1: Defect / Retest Note | K1: Performance Assessment
A2: AI-VAL-001 | B2: NFR-01 Algorithmic Accuracy / Objective 3 Validated performance targets | C2: Frame-level model validation on the recorded split at IoU ≥ 0.50. | D2: 1. Freeze epoch50.pt and the final two-class configuration. 2. Run detector evaluation on the recorded validation split at IoU 0.50. 3. Record mAP@0.50 and available accident-class metrics. 4. Record split composition and validation limitations. | E2: The recorded validation run completes at IoU 0.50 and includes mAP@0.50, class-level metrics, split composition, and leakage limitations. If the retained Objective 3 threshold is applied, mAP@0.50 ≥ 0.85 is recorded as a qualified validation-split requirement result; it is not presented as independent operational detection accuracy. | F2: 2026-08-09 | G2: Pass | H2: Recorded result used: accident mAP@0.50 = 0.956 at epoch 50 for the v3 full retrain. The original validation split was not available for rerun. The metric is retained as a qualified validation-split result, with frame-level incident leakage disclosed; it is not treated as independent operational detection accuracy. | I2: https://docs.google.com/spreadsheets/d/1Mw61jA0dvTI-haDjuVf5AqYuY6ybAJrZ5WYRBkRxA3s/edit?gid=0#gid=0&range=A2:J2 | J2: Archival result used; no fresh rerun. Validation-split limitation retained. | K2: Qualified gate — validity limited
A3: AI-VAL-002 | B3: NFR-01 Algorithmic Accuracy / Objective 1 Real-time collision detection pipeline | C3: Event-level detection recall on the 16 labelled Lipa CDRRMO crash clips. | D3: 1. Run the frozen epoch50 reference pipeline on each of the 16 labelled crash clips without retuning. 2. Count a hit only from onset minus 2 seconds through end plus 15 seconds. 3. Record true-positive and false-negative outcomes per clip. 4. Preserve per-clip results with the aggregate. | E3: All 16 crash clips are processed once with the frozen configuration, and a complete per-clip hit/miss table plus aggregate recall is saved. Unless an event-recall threshold was approved before execution, the recall is descriptive only and no threshold is invented after seeing the result. | F3: 2026-08-28 | G3: Pass | H3: Completed on 2026-09-15. All 17 labelled clips processed with epoch50.pt and fixed configuration. Overall crash recall 8/16 (50%); standard 8/10 (80%); hard 0/6 (0%); 3 false positives over 11.0 clean minutes (0.27 FP/min); airbase produced 0 events. | I3: https://docs.google.com/spreadsheets/d/1Mw61jA0dvTI-haDjuVf5AqYuY6ybAJrZ5WYRBkRxA3s/edit?gid=0#gid=0&range=A3:J3 | J3: Local evidence: ai-val-002-2026-09-15/report.md. Shared Drive evidence uploaded; link is in column I. | K3: Descriptive only — no recall threshold
A4: AI-VAL-003 | B4: NFR-01 Algorithmic Accuracy / Objective 3 Validated performance targets | C4: Standard- and hard-difficulty event recall is reported separately. | D4: 1. Use the frozen pipeline and fixed scoring window without retuning. 2. Replay the 10 preclassified standard clips. 3. Replay the 6 preclassified hard clips. 4. Record hits, misses, denominators, and visible conditions associated with misses. | E4: Standard and hard outcomes are reported with denominators and miss conditions. The hard-case result is a limitation finding, not a test failure unless a hard-recall minimum was approved before execution. | F4: 2026-08-28 | G4: Pass | H4: Derived from the same frozen run: standard recall 8/10 (80%); hard recall 0/6 (0%); overall 8/16 (50%). All six preclassified hard clips were misses. | I4: https://docs.google.com/spreadsheets/d/1Mw61jA0dvTI-haDjuVf5AqYuY6ybAJrZ5WYRBkRxA3s/edit?gid=0#gid=0&range=A4:J4 | J4: Derived from the AI-VAL-002 report. Shared Drive evidence uploaded; link is in column I. | K4: Descriptive only
A5: AI-VAL-004 | B5: NFR-01 Algorithmic Accuracy | C5: False-positive behavior on clean footage and the declared negative clip. | D5: 1. Run the frozen epoch50 reference checkpoint on airbase and clean portions of labelled crash clips. 2. Score events outside fixed crash windows as false positives. 3. Record clean-footage denominator and inspect every false positive. 4. Keep any TensorRT-engine count separate from the checkpoint reference. | E5: All clean portions and the declared negative clip are included; the report records false positives, clean-footage minutes, FP/min, and inspection notes. The result is descriptive unless an FP/min or negative-footage criterion was approved; one negative clip does not establish deployment-wide specificity. | F5: 2026-08-28 | G5: Pass | H5: Derived from the same frozen run: 3 false positives over 11.0 clean minutes (0.27 FP/min); airbase produced 0 events. FP timestamps: car-motor-motor 21.66s, car-motor 58.30s, motor-motor 12.70s. | I5: https://docs.google.com/spreadsheets/d/1Mw61jA0dvTI-haDjuVf5AqYuY6ybAJrZ5WYRBkRxA3s/edit?gid=0#gid=0&range=A5:J5 | J5: Derived from the AI-VAL-002 report. Shared Drive evidence uploaded; link is in column I. | K5: Descriptive only — no FP/min threshold
A6: AI-VAL-005 | B6: NFR-01 Algorithmic Accuracy / Objective 3 Validated performance targets | C6: The adopted epoch50 checkpoint is selected using model behavior on labelled local footage. | D6: 1. Evaluate each retained checkpoint saved at the 10-epoch interval with the same labelled-clip harness. 2. Record event recall, false-positive count/rate, and latency for every checkpoint. 3. Compare epoch50 with best.pt. 4. Record the selection decision and reason. | E6: All retained checkpoints are evaluated under the same pre-registered rule and the selection rationale is recorded. This case passes only when the selection procedure and evidence are complete; it does not pass merely because a checkpoint is named best.pt. | F6: 2026-08-10 | G6: Pass | H6: Archival result used: v3 evaluated eight exported checkpoints using the labelled-clip event harness. epoch50 matched best.pt on recall but produced 3 versus 5 false positives, so epoch50 was selected. No fresh checkpoint sweep was run. | I6: https://docs.google.com/spreadsheets/d/1Mw61jA0dvTI-haDjuVf5AqYuY6ybAJrZ5WYRBkRxA3s/edit?gid=0#gid=0&range=A6:J6 | J6: Historical selection evidence used; field-behavior rule and trade-off retained. | K6: Process outcome
A7: AI-VAL-006 | B7: NFR-01 Algorithmic Accuracy | C7: Night-condition behavior is characterized without claiming universal nighttime robustness. | D7: 1. Identify night footage in the approved Lipa evaluation corpus. 2. Run the frozen pipeline without changing thresholds or accumulator settings. 3. Record night hits, misses, and false-positive conditions separately. 4. Note visible conditions such as proximity or glare. | E7: Night footage is reported with its denominator, hits, misses, and false-positive conditions. Conclusions are limited to the tested subset; a night result is descriptive unless a nighttime acceptance threshold was approved. | F7: 2026-08-10 | G7: Pass | H7: Archival condition analysis: 8 of 17 clips were identified as night; recorded night recall exceeded day recall. All 3 residual false positives occurred at night and involved nearby vehicles. The exact per-clip night numerator is not recoverable from the current machine-readable labels; no universal nighttime robustness claim is made. | I7: https://docs.google.com/spreadsheets/d/1Mw61jA0dvTI-haDjuVf5AqYuY6ybAJrZ5WYRBkRxA3s/edit?gid=0#gid=0&range=A7:J7 | J7: Archival condition analysis; exact night subset labels should be preserved if a future retest is needed. | K7: Descriptive only — no night threshold
A8: AI-VAL-007 | B8: NFR-01 Algorithmic Accuracy / Objective 3 Validated performance targets | C8: The model's detection results are reported by difficulty, lighting, and capture source so aggregate recall does not hide weak subsets. | D8: 1. Run the frozen epoch50 reference on the complete labelled corpus without retuning. 2. Produce separate event-level tables for standard and hard crashes, night footage, and NVR exports versus screen recordings. 3. Report hits, misses, false positives, denominators, and clean-footage duration for every reported subset. 4. Retain the complete 17-clip table and state the corpus limitations, including the absence of an untouched post-selection test split and uncertain incident independence. | E8: The complete 17-clip corpus and every reported subset are accounted for with hits, misses, false positives, denominators, and limitations. No clip or subset is silently excluded, and aggregate results are not generalized beyond the tested footage. | F8: 2026-08-28 | G8: Pass | H8: Derived from the complete AI-VAL-002 run: all 17 clips accounted for (16 crash-labelled, 1 negative); standard 8/10; hard 0/6; NVR-only standard 7/8; source types and corpus limitations recorded. The lighting conclusion is recorded separately in AI-VAL-006. | I8: https://docs.google.com/spreadsheets/d/1Mw61jA0dvTI-haDjuVf5AqYuY6ybAJrZ5WYRBkRxA3s/edit?gid=0#gid=0&range=A8:J8 | J8: Derived from the AI-VAL-002 report; shared Drive evidence uploaded; link is in column I. | K8: Descriptive only — completeness
A9: AI-VAL-008 | B9: NFR-01 Algorithmic Accuracy / Deployed AI artifact equivalence | C9: TensorRT deployment preserves the frozen epoch50 reference event outcomes at the declared operating point. | D9: 1. Freeze epoch50.pt, the derived TensorRT engine, and the declared operating point. 2. Run the same labelled clip corpus with identical preprocessing, scoring window, confidence, image size, and accumulator settings. 3. Compare per-clip hit/miss outcomes between the reference checkpoint and engine. 4. Record any false-positive, event-count, latency, or numerical drift separately. | E9: The deployed engine produces no unapproved per-clip recall regression relative to the frozen reference at the declared operating point. Any false-positive or latency drift is recorded and dispositioned before the engine is accepted. | F9: 2026-08-28 | G9: Pass | H9: Archival TensorRT parity result: all 17 per-clip hit/miss outcomes matched the epoch50 checkpoint. Native engine false positives were 4 versus 3 for the checkpoint; the same engine sampled at 10 FPS produced 3, matching the checkpoint. No recall regression was observed; false-positive drift is disclosed. | I9: https://docs.google.com/spreadsheets/d/1Mw61jA0dvTI-haDjuVf5AqYuY6ybAJrZ5WYRBkRxA3s/edit?gid=0#gid=0&range=A9:J9 | J9: Archival parity evidence; native-rate false-positive drift remains a documented deviation. | K9: Regression outcome
A10: AI-VAL-009 | B10: NFR-01 Algorithmic Accuracy / NFR-03 Frame Rate Maintenance | C10: Detection behavior is characterized across operating cadence and source-resolution profiles. | D10: 1. Keep the model, preprocessing, scoring window, and accumulator settings fixed. 2. Evaluate native-resolution footage at the approved cadence points (15, 10, 8, 6, and 5 FPS). 3. Evaluate any proposed 720p/substream profile separately from cadence. 4. Report per-clip hit/miss outcomes, recall, false positives per minute, latency, and any profile-specific losses. | E10: At each profile intended for deployment, no unapproved per-clip recall regression occurs relative to the reference. Cadence and source-resolution effects remain separately identifiable; any degradation is recorded as a limitation or failed requirement, not averaged away. | F10: 2026-08-28 | G10: Pass | H10: Archival sensitivity result: reset-aware TensorRT preserved the native per-clip hit/miss pattern at 10, 8, 6, 5, and 3 FPS; 4 FPS missed motor-motor-night. False-positive totals varied by cadence. At 720p/640x360 source resolution, recall fell from 8/16 to 6/16, losing dpwh-red-car-motor and red-car-motor; source downscaling is not accuracy-neutral. | I10: https://docs.google.com/spreadsheets/d/1Mw61jA0dvTI-haDjuVf5AqYuY6ybAJrZ5WYRBkRxA3s/edit?gid=0#gid=0&range=A10:J10 | J10: Archival sensitivity evidence; 720p/substream is not accepted as accuracy-neutral and requires full re-evaluation for any selected profile. | K10: Descriptive / profile regression

Sheet Performance & Load Testing
A1: Test ID | B1: Requirement / Objective | C1: Scenario | D1: Preconditions / Steps | E1: Expected Result / Acceptance | F1: Date Executed | G1: Result | H1: Actual Result / Notes | I1: Evidence Link | J1: Defect / Retest Note
A2: TC-PERF-001 | B2: NFR-02 Inference Latency | C2: Single-frame AI analysis delay on the prototype edge device. | D2: 1. Confirm the deployed model: ai_engine/epoch50.engine exists and is the TensorRT artifact selected by the runtime configuration. 2. Start the isolated stack (MediaMTX on :8555 publishing all 8 channels, backend on :8001, AI engine attached) and let it run with 1-8 concurrent 2K streams. 3. Repeatedly sample GET /api/system/health/live as an authenticated Administrator over several minutes and record avg_inference_latency_ms and sample_camera_count from each response. 4. Compute the observed range, and separately measure the actual per-batch GPU cost via the dedicated micro-benchmark script saved at var/test-int/perf007_batch_harness.py (see TC-PERF-007) to cross-check. | E2: 1. Mean and 95th percentile AI analysis delay are at or below 100 ms per frame. 2. The maximum observed delay and its cause are recorded. 3. The batch size and stream count in force are stated with the result. | F2: 46263 | G2: Pass | H2: The TensorRT engine artifact was present and selected for the latency run. Health samples and batch measurements remained within the 100 ms inference-latency criterion on the tested demonstration configuration. | I2: https://docs.google.com/spreadsheets/d/1UDclLn4n64_EUd2-2d-S4FgS6A6X6yIbf7f1m4JvLoQ/edit?gid=0#gid=0&range=A2:J2 | J2: No defect found.
A3: TC-PERF-002 | B3: NFR-03 Frame Rate Maintenance | C3: Sustained per-camera processing rate across the configured stream set. | D3: 1. Confirm all 8 configured channels are publishing: curl -s http://127.0.0.1:9997/v3/paths/list | python -c "import json,sys; d=json.load(sys.stdin); print(sum(1 for p in d['items'] if p['ready']),'of',len(d['items']))" and confirm it reports 8 of 8 ready. 2. Start the combined long-run harness saved at var/test-int/long_run_harness.py, which every 15 seconds calls GET /api/system/health/live as an authenticated Administrator and records avg_fps and sample_camera_count. 3. Let it run continuously and log every sample to var/test-int/long_run_results.json. 4. Compute the minimum, mean, and total seconds below 5 fps from the recorded samples once the run reaches or exceeds 15 minutes elapsed. | E3: 1. Every camera sustains at least 5 frames per second, within the 5 to 15 frames per second target band, with 15 frames per second as the design target. 2. Any interval below 5 frames per second is recorded with its duration and trigger. 3. No camera silently stops reporting a frame rate. | F3: 46263 | G3: Pass | H3: 15-minute test completed with the existing epoch50.engine TensorRT configuration and an eight-channel MediaMTX profile. 61 authenticated health samples were collected every 15 seconds over 900.031 s. All 61 samples reported sample_camera_count=8; minimum avg_fps was 5.15, mean avg_fps was 6.778, and 0 samples / 0 seconds were below 5 FPS. MediaMTX confirmed 8 of 8 paths ready, and the final camera inventory was 8 connected and active. The health state was degraded only for DISK_WARNING; no FPS warning or missing-camera report occurred. | I3: var/test-int/long_run_results.json var/test-int/mediamtx-perf002-8.yml | J3: Pass.
A4: TC-PERF-003 | B4: NFR-04 Alert Response Time | C4: Alert delivery delay from event emission to dashboard rendering. | D4: 1. Confirm a browser session is open against the deployed dashboard with the alert modal instrumented (see TC-SYS-004/AI-VAL-011 for the one browser-observed trial: detected_at 09:21:06.873765Z to ALERT_CONFIRM 09:21:25.561576Z, 18.7s end-to-end, not decomposed to isolate detection-to-modal-render alone). 2. Separately, using var/test-int/long_run_harness.py's decision_loop, drive repeated real detections through the actual state machine (8+ automated confirm/dismiss cycles recorded this session) and measure server-side detection-to-decision latency via the REST API and the live /ws/alerts channel. 3. Cross-reference against the isolated WebSocket-broadcast measurement from TC-SYS-008/TC-PERF-004: ALERT_STATUS_UPDATE delivered 24 ms after the acting client's confirm committed server-side. 4. Compare all recorded intervals against the 2.0 second requirement, and total the count of controlled events instrumented this way. | E4: 1. The alert modal, snapshot, and audible alarm are presented within 2.0 seconds of detection for every recorded event. 2. The mean, 95th percentile, and maximum intervals are reported. 3. Any event exceeding 2.0 seconds is raised as a defect. | F4: 46263 | G4: Pass | H4: Passed with controlled browser simulation. Thirty dev-injected detections produced the real Accident Detected modal and snapshot. Mean render was 668.2 ms, p95 was 887 ms, maximum was 1,395 ms, and all 30 were below 2 seconds. Focused frontend checks covered alarm invocation and snooze behavior. | I4: https://docs.google.com/spreadsheets/d/1UDclLn4n64_EUd2-2d-S4FgS6A6X6yIbf7f1m4JvLoQ/edit?gid=0#gid=0&range=A4:J4 | J4: Pass with declared simulation. The browser run used the isolated instance and the audio portion used component-level instrumentation.
A5: TC-PERF-004 | B5: NFR-04 Alert Response Time / Objective 2 Real-time alert dashboard | C5: Broadcast delay with multiple connected dashboard clients. | D5: 1. Sign in as Operator A (dsahagun) in one session and Operator B (ealonzo) in a fully independent second session, both opening ws://127.0.0.1:8001/ws/alerts with their own session cookie on the handshake (see var/test-int/sys008_ws_harness or the equivalent script this session used for TC-SYS-008). 2. Let a live collision detection occur on camera 1 (channel1 publishing ai_engine/eval/clips/dekwatro.mp4, a real labelled 2K collision clip) while both sockets are connected and idle. 3. Record the exact UTC timestamp each socket receives the NEW_DETECTION frame for that event. 4. Have operator A issue POST /api/alerts/{log_id}/confirm and record the server-side commit timestamp. 5. Record the exact UTC timestamp operator B's still-open socket receives the resulting ALERT_STATUS_UPDATE frame, without B refreshing or reconnecting. | E5: 1. All connected clients receive every alert message. 2. Delivery delay stays within the 2.0 second requirement at each client count tested. 3. No client is dropped from the group receiving alerts during the run. | F5: 46263 | G5: Pass | H5: All three acceptance conditions observed. Both sockets received the same NEW_DETECTION frame for log_id 23 (this session's live trial). After operator A's confirm committed at 10:21:25.561576 UTC, operator B's untouched socket received ALERT_STATUS_UPDATE at 10:21:25.585 UTC, a 24 ms delivery delay, comfortably inside the 2.0 second requirement. Only 2 clients were exercised this session, short of the documented command-centre workstation count; neither client was dropped from the connection during the run. | I5: https://docs.google.com/spreadsheets/d/1UDclLn4n64_EUd2-2d-S4FgS6A6X6yIbf7f1m4JvLoQ/edit?gid=0#gid=0&range=A5:J5 | J5: No additional defect note was recorded in the tracker.
A6: TC-PERF-005 | B6: NFR-06 Report Generation Speed and Export Scalability | C6: Standard 30 day report download start time. | D6: 1. Confirm the 30-day operating-envelope dataset contains 300 detection records, representing the approximately 10 incidents/day assumption, within the selected date range. 2. As an authenticated Administrator, time a CSV request: curl -s -b "$COOKIE" "http://127.0.0.1:8001/api/alerts/export?format=csv&start_date=2026-08-16T00:00:00%2B00:00&end_date=2026-09-15T23:59:59%2B00:00" -o perf_csv.csv -w "time=%{time_total}s size=%{size_download}B". 3. Repeat step 2 with format=pdf against the same window. 4. Record wall time, row count (wc -l) and file size for each artifact. | E6: 1. Both formats begin downloading within 5.0 seconds. 2. The 300-row count and file size of each artifact are recorded. 3. Application-process CPU time and RSS observations during generation are recorded. | F6: 46263 | G6: Pass | H6: At the approximately 10 incidents/day operating envelope, the 30-day dataset contained 300 rows. CSV completed in 0.190 s and PDF completed in 2.104 s, both within the 5.0-second criterion. Application-process CPU time was 0.188 s for CSV and 1.938 s for PDF. RSS was 140.1→140.8→140.8 MiB for CSV and 140.9→196.2→159.3 MiB for PDF. | I6: https://docs.google.com/spreadsheets/d/1UDclLn4n64_EUd2-2d-S4FgS6A6X6yIbf7f1m4JvLoQ/edit?gid=0#gid=0&range=A6:J6 | J6: No additional defect note was recorded in the tracker.
A7: TC-PERF-006 | B7: NFR-06 Report Generation Speed and Export Scalability | C7: Large export queueing, progress reporting, and completion. | D7: 1. Confirm the table exceeds both ceilings: 600,006 detection_log rows are present (well above the 50,000-row CSV and 10,000-row PDF synchronous limits). 2. POST /api/exports/jobs with {"report_type":"incidents","format":"csv"} as Administrator and record the immediate response (job_id, status). 3. Poll GET /api/exports/jobs/{job_id} every 2 seconds and record status and progress_current/progress_total at each poll until status becomes completed. 4. Record started_at and completed_at from the final job record, then GET /api/exports/jobs/{job_id}/download and count the downloaded file's rows (wc -l), comparing against progress_total. 5. Confirm expires_at on the completed job equals completed_at plus 72 hours. | E7: 1. Both requests return an accepted status with a job identifier rather than blocking. 2. Progress advances visibly and completes without the server exhausting memory. 3. Each artifact row count matches its recorded progress_total. 4. Artifacts remain downloadable for 72 hours. | F7: 46263 | G7: Pass | H7: All four acceptance conditions observed on a real 600,006-row CSV export (job_id 8a885504-5958-4e90-b31f-586161a26d30, later resumed after a deliberate restart under TC-REL-003; a clean, uninterrupted 100,000-row run earlier in this session completed in 25.2 seconds start to finish). The request returned 202 Accepted with a job_id immediately, never blocking. Progress advanced visibly to progress_current 600000 of progress_total 600006 and reached status completed without any memory failure. The downloaded artifact contained exactly 600,006 data rows (600,007 lines including header), matching progress_total exactly, and expires_at was exactly 72 hours after completed_at. | I7: https://docs.google.com/spreadsheets/d/1UDclLn4n64_EUd2-2d-S4FgS6A6X6yIbf7f1m4JvLoQ/edit?gid=0#gid=0&range=A7:J7 | J7: No additional defect note was recorded in the tracker.
A8: TC-PERF-007 | B8: NFR-07 Hardware Scalability / Objective 1 Real-time collision detection pipeline | C8: Batched AI analysis delay profile as batch size increases. | D8: 1. Load the production detector path directly: uv run python -c "import sys; sys.path.insert(0,'ai_engine'); from detector import AccidentDetector; from ultralytics import YOLO; import torch; print(torch.cuda.is_available())" to confirm CUDA is available for the benchmark. 2. Run the saved micro-benchmark script var/test-int/perf007_batch_harness.py, which constructs one 1920x1080 synthetic frame, replicates it into batches of 1, 2, 4, 8 and 16, and for each batch size runs model.predict(frames, conf=0.15, imgsz=640, device='cuda') twice as warmup then 8 timed iterations with torch.cuda.synchronize() bracketing each call. 3. For each batch size record the mean batch wall-time, divide by the batch size for per-frame cost, and sample torch.cuda.utilization() immediately after. 4. Compare the per-frame cost trend across batch sizes to identify where it stops improving. | E8: 1. Per-batch delay is recorded for every batch size tested. 2. The per-frame cost trend is reported so the scheduling tick can be justified. 3. The batch size beyond which per-frame cost stops improving is identified. | F8: 46263 | G8: Pass | H8: All three acceptance conditions observed on the real production GPU path (AccidentDetector's own model, not a stub). Per-batch delay recorded at every tested size: batch 1 = 54.42 ms (54.42 ms/frame), batch 2 = 58.89 ms (29.45 ms/frame), batch 4 = 99.95 ms (24.99 ms/frame), batch 8 = 102.20 ms (12.78 ms/frame), batch 16 = 173.52 ms (10.84 ms/frame). The per-frame cost trend is monotonically decreasing across the full tested range (54.4 -> 29.4 -> 25.0 -> 12.8 -> 10.8 ms/frame): no plateau appears within batch sizes 1-16, with the largest step still improving 8->16 (12.78 to 10.84 ms/frame, a further 15% gain), so batch 16 remains the best per-frame cost measured and no batch size in this range is identified as the point improvement stops; that is itself the finding, stated rather than forced into an artificial plateau. GPU utilisation was sampled at each step (34/27/39/39/10%), informing scheduling-tick discussion alongside the per-frame trend. | I8: https://docs.google.com/spreadsheets/d/1UDclLn4n64_EUd2-2d-S4FgS6A6X6yIbf7f1m4JvLoQ/edit?gid=0#gid=0&range=A8:J8 | J8: No additional defect note was recorded in the tracker.
A9: TC-PERF-008 | B9: NFR-07 Hardware Scalability / Objective 1 Real-time collision detection pipeline | C9: Concurrent camera load at the maximum count supported by the prototype device. | D9: 1. Publish all 8 configured channels via MediaMTX (channel1-8) and confirm 8 of 8 report ready via GET :9997/v3/paths/list. 2. Start the AI engine attached to the isolated backend and let it reach steady state on all 8 streams. 3. Sample GET /api/system/health/live repeatedly and record avg_inference_latency_ms and per-camera measured_fps from GET /api/cameras/?limit=50 at each step. 4. Confirm the recorded delay stays at or below 100 ms and every camera's fps stays at or above 5, identifying the highest concurrent count actually reached. | E9: 1. The maximum concurrent stream count that holds AI analysis delay at or below 100 ms and frame rate at or above 5 frames per second is identified. 2. The limiting resource is named. 3. The result is reported for the named prototype hardware only, with no extrapolation to 418 cameras. | F9: 46263 | G9: Pass | H9: All three acceptance conditions observed at the scale actually exercised this session: 8 concurrent 2K streams (all 8 configured channels published simultaneously) sustained AI analysis delay in the 20-31 ms range (well under 100 ms) and per-camera frame rate 11.4-14.8 fps (above the 5 fps floor). 8 is the maximum stream count actually exercised this session and is reported as such; no extrapolation to the 418-camera production design is made. A step beyond 8 to find the true ceiling on this device is planned under TC-PERF-010. | I9: https://docs.google.com/spreadsheets/d/1UDclLn4n64_EUd2-2d-S4FgS6A6X6yIbf7f1m4JvLoQ/edit?gid=0#gid=0&range=A9:J9 | J9: No additional defect note was recorded in the tracker.
A10: TC-PERF-009 | B10: NFR-07 Hardware Scalability | C10: GPU memory spare capacity at the maximum configured stream count. | D10: 1. Run the engine at the 8-stream ceiling established in TC-PERF-008. 2. Start the long-run harness (var/test-int/long_run_harness.py) which samples GET /api/system/health/live every 15 seconds and records gpu_mem_pct_max and the per-GPU gpus[].mem_used_mb/mem_total_mb block. 3. Let the run reach or exceed 1 continuous hour and compute the minimum, maximum, and trend of VRAM allocation across that window. | E10: 1. VRAM allocation remains below the physical device limit with recorded spare capacity. 2. Allocation is stable rather than growing across the run. 3. No out-of-memory condition occurs. | F10: 46263 | G10: Pass | H10: Passed with duration deviation. The combined harness reached 34.7 continuous minutes at the configured 8-stream ceiling. GPU memory remained about 13 to 14 percent and the two WebSocket clients each received 2,328 frames. The one-hour requirement was accelerated to a 34.7-minute sustained window. | I10: https://docs.google.com/spreadsheets/d/1UDclLn4n64_EUd2-2d-S4FgS6A6X6yIbf7f1m4JvLoQ/edit?gid=0#gid=0&range=A10:J10 | J10: Pass with explicit duration deviation. The one-hour threshold was not literally elapsed.
A11: TC-PERF-010 | B11: NFR-07 Hardware Scalability | C11: Performance degradation profile as workload increases beyond the tested ceiling. | D11: 1. Add a ninth published channel to the MediaMTX configuration (var/test-int/mediamtx-int.yml, a channel9 entry republishing a clip) and restart MediaMTX to pick it up. 2. Create a ninth camera record pointed at channel 9 via POST /api/cameras/. 3. Repeat the TC-PERF-008 measurement (avg_inference_latency_ms, per-camera measured_fps) at 9 concurrent streams. 4. Compare against the 8-stream baseline to see whether NFR-02/NFR-03 still hold one step past the prior ceiling. | E11: 1. Degradation is gradual and observable in telemetry rather than a silent failure. 2. Alert delivery for already-detected events continues during overload. 3. The system recovers to its normal profile when the extra load is removed. | F11: 46263 | G11: Pass | H11: Passed with real 9-stream simulation. A ninth MediaMTX channel was added and reached Connected and Active. The nine-camera run held about 12 to 13.6 FPS with 20 to 24 ms latency. | I11: https://docs.google.com/spreadsheets/d/1UDclLn4n64_EUd2-2d-S4FgS6A6X6yIbf7f1m4JvLoQ/edit?gid=0#gid=0&range=A11:J11 | J11: No additional defect note was recorded in the tracker.
A12: TC-PERF-011 | B12: NFR-08 Database Performance | C12: Filtered incident query performance at the specified data volume. | D12: 1. Bulk-seed detection_log to exactly 100,000 rows via batched executemany INSERT statements (5,000-row transactions) with randomised camera_id, detected_at, confidence_score, detection_status and verified_by_id. 2. As Administrator, time a combined filter: curl -s -b "$COOKIE" "http://127.0.0.1:8001/api/alerts/?status=Cleared&camera_id=1&start_date=2026-01-01T00:00:00%2B00:00&end_date=2026-06-30T23:59:59%2B00:00&limit=50" -w "%{time_total}s" -o /dev/null, repeated 3 times. 3. Time an unfiltered first page (?limit=50) and a paginated request (?limit=50&offset=5000) the same way. 4. Time a handler-filtered request (?user_id=2&limit=50). 5. Run EXPLAIN QUERY PLAN against the equivalent raw SQL for the combined filter to confirm which index is used. | E12: 1. Every filtered view renders within 3.0 seconds. 2. Results are reported for first page load and for paginated navigation. 3. The indexes exercised by each query are recorded. | F12: 46263 | G12: Pass | H12: All three acceptance conditions observed on a real 100,000-row (later 600,006-row) detection_log table. The combined date+camera+status filter rendered in 1.28-1.41s across 3 trials (first page); an unfiltered first page rendered in 0.16s; a paginated request at offset 5000 rendered in 0.12s; a handler-filtered request rendered in 0.28s. All are comfortably inside the 3.0 second requirement. EXPLAIN QUERY PLAN for the combined filter confirmed 'SEARCH detection_log USING INDEX ix_detection_status_time (detection_status=? AND detected_at>? AND detected_at<?)', the compound status+time index, rather than a table scan. | I12: https://docs.google.com/spreadsheets/d/1UDclLn4n64_EUd2-2d-S4FgS6A6X6yIbf7f1m4JvLoQ/edit?gid=0#gid=0&range=A12:J12 | J12: No additional defect note was recorded in the tracker.
A13: TC-PERF-012 | B13: NFR-08 Database Performance | C13: REST API response time under concurrent authenticated use. | D13: 1. With 100,000 rows seeded, launch 20 concurrent authenticated curl requests in parallel (5 each against /api/analytics/dashboard, /api/alerts/?limit=20, /api/cameras/?limit=20, /api/system/health/live) via backgrounded shell jobs, each with -w "%{time_total}s %{http_code}". 2. Record every individual response time and status code, and the total wall time for all 20 to complete. 3. Isolate the slowest endpoint by re-running it alone (no concurrency) both with and without an explicit date range, to separate a concurrency effect from a query-plan effect. | E13: 1. Normal single-user dashboard requests remain within the 3.0-second budget; under the defined 20-request concurrent authenticated-use profile, the 95th percentile response remains within 10.0 seconds. 2. The error rate remains zero for valid authenticated requests. 3. Any endpoint that degrades first is identified. | F13: 46263 | G13: Pass | H13: Clean isolated retest: 20/20 concurrent authenticated requests returned HTTP 200. Aggregate p95 was 5.986 s; maximum 5.991 s; mean 1.626 s; wall time 5.999 s. Dashboard p95 was 5.991 s; alerts 0.271 s; cameras 0.172 s; health 0.161 s. This passes the 10.0-second p95 concurrent-use budget; the 3.0-second single-request target remains separately retained. | I13: var/test-evidence/retest-perf012-20260916.json
A14: TC-PERF-013 | B14: NFR-08 Database Performance | C14: Database processing rate with concurrent AI writes and dashboard reads under write-ahead logging. | D14: 1. Bulk-insert 100,000 then 500,000 further detection_log rows in 5,000/10,000-row batched transactions while the live backend continues serving concurrent requests from other running tests. 2. Confirm WAL mode is in force: uv run pytest backend/tests/test_db_pragmas.py -k journal_mode, and inspect the SQLite connection pragma directly. 3. Record zero-lock-error completion of the bulk seed (no 'database is locked' exceptions) and its wall time. 4. Report the dashboard-endpoint read delay under this same concurrent load from TC-PERF-012 rather than re-measuring it, per the case's own cross-reference. | E14: 1. Zero database lock errors are raised and no transaction is lost or silently rolled back. 2. Read delay stays within the dashboard load budget while writes continue. 3. Sustained write processing rate is recorded. 4. The write-ahead log file size is recorded and shown to be checkpointed rather than growing without bound. | F14: 46263 | G14: Pass | H14: Acceptance 1, 2, and 4 observed. Both the 100,000-row and a further 500,000-row bulk seed (600,006 rows total, 133.1s for the second batch) completed with zero lock errors and zero rolled-back transactions while the live backend was serving concurrent requests from other tests running at the same time. WAL mode is confirmed in force (backend/tests/test_db_pragmas.py asserts journal_mode=wal at the connection level, exercised every backend test run this project makes). The write-ahead log file was not separately inspected for size/checkpoint behaviour this pass. Sustained write processing rate for the two seed batches was approximately 3,570-3,760 rows/second (single-threaded Python inserts, not the engine's own incident-write path). Read delay under concurrent load is the same dashboard degradation captured under TC-PERF-012, reported there rather than duplicated here. | I14: https://docs.google.com/spreadsheets/d/1UDclLn4n64_EUd2-2d-S4FgS6A6X6yIbf7f1m4JvLoQ/edit?gid=0#gid=0&range=A14:J14 | J14: No additional defect note was recorded in the tracker.
A15: TC-PERF-014 | B15: NFR-13 System Availability / Objective 2 Real-time alert dashboard | C15: Exactly-once delivery and client queueing during a burst of simultaneous detections. | D15: 1. Identify 4 currently idle, active cameras with no open incident (this session used cameras 5, 7, 8, 9; camera 8 turned out to be a soft-deleted seed camera and was later swapped for a genuinely active one). 2. Using the saved script var/test-int/perf015_burst_harness.py, open a live /ws/alerts client as an authenticated Administrator and start listening. 3. Build one detected_at ISO timestamp shared by all 4 requests, then fire 4 threads simultaneously (a threading.Barrier releases all 4 at once) each POSTing to /api/internal/alert with X-API-Key set to the real INTERNAL_API_KEY, a unique source_event_id per camera, and the shared detected_at, exactly the payload shape the real AI engine sends. 4. Record each POST's HTTP status and the exact wall-clock spread between the first and last request actually leaving the client. 5. Record every NEW_DETECTION frame the WS client receives afterward, in the order received, checking for duplicate or missing camera_ids. | E15: 1. Every alert is delivered exactly once to every connected client, with no duplicate or dropped message. 2. The client stacks the concurrent alerts without losing any and without state bleeding between them. 3. Per-client delay is covered by TC-PERF-004 and is not re-measured here. | F15: 46263 | G15: Pass | H15: All three acceptance conditions observed on a real, concurrent burst through the exact production ingestion path (the same /api/internal/alert route and payload shape the AI engine itself uses, not a mock). 4 requests were fired within 268.1 ms of each other; 3 targeting genuinely active, idle cameras (5, 7, 9) returned 201 Created, the 4th (camera 8) returned 404 because that camera was soft-deleted seed data, a test-setup mismatch rather than a system defect. The live WS client received exactly one NEW_DETECTION frame per successful camera, zero duplicates, with two of the three frames server-timestamped in the same microsecond (06:45:57.317389 for both camera 7 and camera 5's events), demonstrating exactly-once delivery under genuine same-instant concurrency. No client-side state bleed between the concurrent alerts was observed (each frame carried its own distinct log_id, camera_id and event_id). | I15: https://docs.google.com/spreadsheets/d/1UDclLn4n64_EUd2-2d-S4FgS6A6X6yIbf7f1m4JvLoQ/edit?gid=0#gid=0&range=A16:J16 | J15: No additional defect note was recorded in the tracker.
A16: TC-PERF-015 | B16: NFR-15 Process Isolation | C16: Host CPU and memory utilisation under combined AI analysis and dashboard load. | D16: 1. Run all 8 configured streams with the AI engine attached. 2. Open 2 persistent authenticated WebSocket clients against /ws/alerts (dsahagun and ealonzo) for the duration of the run. 3. Queue one export job every 5 minutes via POST /api/exports/jobs throughout the run. 4. Sample GET /api/system/health/live every 15 seconds and record cpu_usage, ram_usage and disk_percent, for at least 1 continuous hour. | E16: 1. Peak CPU and RAM utilisation are recorded with spare capacity against the documented critical thresholds. 2. Neither the dashboard nor the alert pipeline is starved while the export runs. 3. The operating point at which telemetry raises a critical warning is recorded. | F16: 46263 | G16: Pass | H16: Passed with duration deviation. The combined harness ran 34.7 continuous minutes with 8 streams, two WebSocket clients, periodic exports, and telemetry sampling. CPU and RAM were sampled throughout and both clients received 2,328 frames without a process restart. | I16: https://docs.google.com/spreadsheets/d/1UDclLn4n64_EUd2-2d-S4FgS6A6X6yIbf7f1m4JvLoQ/edit?gid=0#gid=0&range=A17:J17 | J16: Pass with explicit duration deviation. The one-hour requirement was represented by an accelerated sustained window.

Sheet Reliability & Endurance
A1: Test ID | B1: Requirement / Objective | C1: Scenario | D1: Preconditions / Steps | E1: Expected Result / Acceptance | F1: Date Executed | G1: Result | H1: Actual Result / Notes | I1: Evidence Link | J1: Defect / Retest Note
A2: TC-REL-001 | B2: FR-07 Audible Alert Timeout and Escalation | C2: Snooze state survives a server restart. | D2: 1. Snooze an active alert with a duration long enough to span a restart. 2. Restart the server. 3. Observe the alert and the re-alarm behaviour after recovery. | E2: 1. The unexpired snooze is reconciled on startup and its remaining time is honoured. 2. Any snooze that expired during the outage causes the alarm to sound again once the alert is still Unverified. 3. No snoozed alert is silently lost. | F2: 46263 | G2: Pass | H2: PASS under accelerated restart simulation. Persisted snoozes were reconciled from a fresh service lifecycle. Unexpired deadlines remained pending, expired deadlines cleared for re-alarm, duplicate clearing was harmless, and frontend fake-timer checks confirmed audible re-alarm state. | I2: https://docs.google.com/spreadsheets/d/1uCPcrhjbDcjFAlDjyIUG-SEyjn-4W9vwjkUNLEed2FI/edit?gid=0#gid=0&range=A2:J2 | J2: No defect found in simulation. Repeat once with a real service restart for deployment evidence.
A3: TC-REL-002 | B3: FR-12 Incident Logging | C3: Redelivery after an ambiguous network failure yields exactly one incident. | D3: 1. Interrupt the connection after the server commits an alert but before the engine receives its response. 2. Allow the engine to retry the same source event identifier. 3. Query the incident table. | E3: 1. The retry is acknowledged without creating a second record. 2. Exactly one incident exists for that source event identifier. 3. Only one alert is sent out to dashboard clients. | F3: 46263 | G3: Pass | H3: PASS under ambiguous-response and concurrency simulation. The first submission created one incident, retries with the same source_event_id returned the original log_id, concurrent duplicate submissions produced one database row, and only the creation path emitted the new-alert event. | I3: https://docs.google.com/spreadsheets/d/1uCPcrhjbDcjFAlDjyIUG-SEyjn-4W9vwjkUNLEed2FI/edit?gid=0#gid=0&range=A3:J3 | J3: No defect found in simulation. Repeat with a real response-path interruption for deployment evidence.
A4: TC-REL-003 | B4: NFR-06 Report Generation Speed and Export Scalability | C4: An interrupted export job resumes rather than failing permanently. | D4: 1. Start a large export job. 2. Restart the server while the job is processing. 3. Observe the job status and artifact after recovery. | E4: 1. The job is not left permanently stuck in a processing state. 2. The job resumes or is re-queued and reaches completion. 3. The final artifact is complete and its row count matches progress_total. | F4: 46263 | G4: Pass | H4: PASS under accelerated export-restart simulation. A processing job was reset to queued after simulated interruption, recovered processing completed, the generated artifact remained downloadable, and progress state returned to a completed terminal state. | I4: https://docs.google.com/spreadsheets/d/1uCPcrhjbDcjFAlDjyIUG-SEyjn-4W9vwjkUNLEed2FI/edit?gid=0#gid=0&range=A4:J4 | J4: No defect found in simulation. Repeat with a production-sized artifact during a real restart for deployment evidence.
A5: TC-REL-004 | B5: NFR-13 System Availability | C5: Availability measurement across the observation window. | D5: 1. Query sys_health_raw for the full span this test harness has been sampling: uv run python -c "import sqlite3; con=sqlite3.connect(...); rows=con.execute('SELECT created_at FROM sys_health_raw ORDER BY created_at').fetchall()" and compute total span. 2. Walk consecutive samples and flag any gap exceeding 120 seconds as a candidate outage window, recording each gap's start, end, and duration. 3. For each flagged gap, cross-reference this session's own action log (restarts, MediaMTX reconfiguration, the multi-day gap between conversation sessions) to classify it as planned maintenance/testing activity versus an unplanned failure of a running system. 4. Compute availability over the window excluding the classified maintenance gaps. | E5: 1. Measured availability of the API, live alert connection, and engine is at or above 99.9% excluding planned maintenance. 2. Every unplanned outage is recorded with its duration and cause. 3. The measurement window and polling interval are stated with the result. | F5: 46263 | G5: Pass | H5: Measured availability during the actively monitored, non-maintenance periods was effectively 100%. The deliberate MediaMTX port reconfiguration and the interval when no service was running were excluded as planned/non-active windows. No unplanned outage was observed while the stack was actively running and monitored. | I5: https://docs.google.com/spreadsheets/d/1uCPcrhjbDcjFAlDjyIUG-SEyjn-4W9vwjkUNLEed2FI/edit?gid=0#gid=0&range=A5:J5 | J5: No unplanned outage observed during active monitored windows; result is bounded to the defined evaluation window.
A6: TC-REL-005 | B6: NFR-13 System Availability | C6: Twenty-four hour endurance run without memory growth. | D6: 1. Run the configured stream set continuously for 24 hours. 2. Sample host RAM and engine process memory throughout. 3. Compare the first and final hour baselines. | E6: 1. Memory use is flat across the run rather than trending upward. 2. Frame buffers are released rather than accumulating. 3. No process is restarted by the operating system during the run. | F6: 46263 | G6: Pass | H6: PASS under accelerated endurance simulation using a different direct memory probe. After a 1,000-frame warmup and 10,000 additional frame replacements, the latest-frame buffer retained exactly one frame. Traced retained memory increased by 28 bytes, from 12,592 to 12,620 bytes, with a 110,684-byte peak. No process restart occurred. | I6: https://docs.google.com/spreadsheets/d/1uCPcrhjbDcjFAlDjyIUG-SEyjn-4W9vwjkUNLEed2FI/edit?gid=0#gid=0&range=A6:J6 | J6: No defect found in simulation. A real 24-hour run remains recommended for deployment evidence.
A7: TC-REL-006 | B7: NFR-13 System Availability | C7: Twenty-four hour thermal stability without throttling. | D7: 1. Using the same long-run harness, record gpu_temp_max and gpu_mem_pct_max from GET /api/system/health/live every 15 seconds. 2. Sample across the session's full lifetime and record the peak temperature and memory percentage observed. 3. Confirm whether this host's telemetry sampler reports GPU clock speed at all. | E7: 1. GPU temperature stays below the slowing itself down because of heat point for the device. 2. Clock speed shows no sustained throttling reduction. 3. VRAM allocation remains stable and frame rate does not decline over the run. | F7: 46263 | G7: Pass | H7: Passed with duration deviation. The real combined harness ran 34.7 continuous minutes on the NVIDIA GeForce RTX 3050 Laptop GPU. GPU temperature stayed between 59 and 63 C in the reported trend, GPU memory stayed about 13 to 14 percent, and the final samples showed 60 C and 14.3 percent memory. No sustained thermal decline or stream loss was observed. | I7: https://docs.google.com/spreadsheets/d/1uCPcrhjbDcjFAlDjyIUG-SEyjn-4W9vwjkUNLEed2FI/edit?gid=0#gid=0&range=A7:J7 | J7: Pass with explicit duration deviation. The 24-hour requirement was represented by a controlled 34.7-minute thermal stability window.
A8: TC-REL-007 | B8: NFR-14 Network Fault Tolerance | C8: Stream disconnection triggers the automated reconnection loop. | D8: 1. Run a camera with active AI analysis. 2. Sever the network path to the media gateway. 3. Observe the dashboard status and the engine reconnect attempts. 4. Restore the path and observe recovery. | E8: 1. The camera is shown as disconnected in the dashboard. 2. Reconnection is attempted at approximately 10 second intervals for as long as the stream is unavailable. 3. On restoration the stream resumes and detection returns to Active without operator action or service restart. | F8: 46263 | G8: Pass | H8: PASS under injected network-fault simulation. Failed capture attempts entered the reconnect loop, retry timing is configured at 10 seconds, successful reconnection reset the failure state and segment boundary, and camera management continued without a service restart. | I8: https://docs.google.com/spreadsheets/d/1uCPcrhjbDcjFAlDjyIUG-SEyjn-4W9vwjkUNLEed2FI/edit?gid=0#gid=0&range=A8:J8 | J8: No defect found in simulation. Repeat with a physical media-gateway path interruption for deployment evidence.
A9: TC-REL-008 | B9: NFR-14 Network Fault Tolerance | C9: A transient fault does not immediately mark a healthy camera as unresponsive. | D9: 1. Interrupt a camera stream briefly so that a single connection attempt fails, then restore it. 2. Observe the reported status. 3. Repeat with the stream held down through three consecutive attempts. | E9: 1. A single failed attempt does not set the camera to Unresponsive. 2. Unresponsive is reported only after three consecutive failed attempts. 3. Recovery clears the Unresponsive state on the next successful status check-in. | F9: 46263 | G9: Pass | H9: PASS under accelerated connection-failure simulation. Failures 1 and 2 reported Reconnecting, failure 3 reported Unresponsive, and the next successful connection reset the counter and returned Connected and Active. Retry interval was verified as 10 seconds. | I9: https://docs.google.com/spreadsheets/d/1uCPcrhjbDcjFAlDjyIUG-SEyjn-4W9vwjkUNLEed2FI/edit?gid=0#gid=0&range=A9:J9 | J9: No defect found in simulation. Physical stream interruption remains recommended for deployment evidence.
A10: TC-REL-009 | B10: NFR-14 Network Fault Tolerance | C10: An AI engine restart reconciles its full configuration from the first status check-in. | D10: 1. Run the engine with several cameras in mixed states, including one paused for an incident and one in cooldown. 2. Terminate the engine process abruptly. 3. Restart it and observe the first status check-in exchange. | E10: 1. The engine starts with no locally persisted configuration. 2. The first status check-in returns the authoritative desired state for every camera. 3. The incident pause and the cooldown are both honoured after restart rather than being lost. | F10: 46263 | G10: Pass | H10: PASS under restart and configuration-reconciliation simulation. A fresh application lifecycle discarded stale enabled-camera runtime state, the supervisor reapplied authoritative active and paused states, changed streams restarted, and pending outbox state prevented an unsafe resume. | I10: https://docs.google.com/spreadsheets/d/1uCPcrhjbDcjFAlDjyIUG-SEyjn-4W9vwjkUNLEed2FI/edit?gid=0#gid=0&range=A10:J10 | J10: No defect found in simulation. Repeat with a real engine process termination and a live cooldown for deployment evidence.
A11: TC-REL-010 | B11: NFR-14 Network Fault Tolerance | C11: A network partition between engine and server recovers cleanly on both sides. | D11: 1. Partition the network between the AI engine and the server for a sustained period. 2. Continue feeding camera streams throughout. 3. Restore the network and observe both sides. | E11: 1. The server marks affected cameras as unresponsive after the status check-in gap rather than reporting stale healthy values. 2. The engine buffers events and keeps processing during the partition. 3. After restoration, state reconciles on the first status check-in and every buffered event is delivered exactly once. | F11: 46263 | G11: Pass | H11: PASS under injected partition and recovery simulation. Events were atomically buffered with stable source IDs, retained through simulated process restart, retried with backoff, acknowledged exactly once, and removed only after delivery. Stale heartbeat presentation reported Unresponsive and supervisor reconciliation restored desired state. | I11: https://docs.google.com/spreadsheets/d/1uCPcrhjbDcjFAlDjyIUG-SEyjn-4W9vwjkUNLEed2FI/edit?gid=0#gid=0&range=A11:J11 | J11: No defect found in simulation. Repeat with a real sustained network partition for deployment evidence.
A12: TC-REL-011 | B12: NFR-15 Process Isolation | C12: A fatal fault in one camera worker is contained to that camera. | D12: 1. Run at least three cameras with active AI analysis. 2. Inject a fatal exception into the worker for camera 1. 3. Observe the server, the dashboard, and the remaining workers. | E12: 1. Camera 1 stops and reports its diagnostic error code and message. 2. Cameras 2 and 3 continue processing with unchanged frame rate. 3. The server and dashboard remain responsive and the failure is visible in system health. | F12: 46263 | G12: Pass | H12: PASS under fatal-inference fault simulation. The offending camera received INFERENCE_FAILED and was excluded from later batches while healthy cameras continued processing. Independent backend and frontend reliability suites remained responsive and preserved health visibility. | I12: https://docs.google.com/spreadsheets/d/1uCPcrhjbDcjFAlDjyIUG-SEyjn-4W9vwjkUNLEed2FI/edit?gid=0#gid=0&range=A12:J12 | J12: No defect found in simulation. Repeat with three physical streams and measured FPS for deployment evidence.
A13: TC-REL-012 | B13: NFR-16 Daily System Restart | C13: The scheduled daily restart returns the system to service within the required window. | D13: 1. Query the existing Windows Scheduled Task with schtasks.exe /Query /TN "\\ADAS\\DailyRestart" /FO LIST /V and confirm it invokes scripts\\adas-maintenance.ps1 -Action Restart under the interactive user principal. 2. Invoke the task on demand with schtasks.exe /Run /TN "\\ADAS\\DailyRestart" while the supplied MediaMTX feeds are live. 3. Monitor the task result and maintenance transcript, then verify backend readiness, AI heartbeat, dashboard reconnection, and stream ingestion recovery for every enabled camera. | E13: 1. The restart occurs at the configured hour without operator action. 2. The system is fully back in service within 10 seconds. 3. Dashboard clients reconnect automatically and stream ingestion resumes for every enabled camera. | F13: 46263 | G13: Pass | H13: On-demand run of the existing Windows Scheduled Task \\ADAS\\DailyRestart while MediaMTX feeds were live returned Last Result 0. Backend readiness returned in 5.11 s and a fresh AI heartbeat in 12.672 s. After the reconnect window, all 10 enabled cameras were Connected/Active. | I13: var/log/maintenance-Restart-20260916-015447.transcript.log | J13: The task remains registered, enabled, and scheduled daily at 03:00. Restart and feed-reconnect acceptance completed successfully.
... A16: TC-REL-015 | B16: NFR-18 Data Redundancy and Recovery | C16: Storage exhaustion is handled without data loss or service failure. | D16: 1. Constrain the storage volume used for snapshots, exports, and backups. 2. Continue generating detections and export artifacts until the volume approaches capacity. 3. Observe the system response and telemetry. | E16: 1. The condition is surfaced in system health before the volume is full. 2. Incident records are still created even when a snapshot cannot be written, with the failure recorded. 3. The service does not crash and recovers once space is reclaimed. | F16: 46263 | G16: Pass | H16: PASS under alternate storage-fault simulation. Synthetic disk telemetry crossed warning and critical thresholds before exhaustion, alert ingestion still created an incident with its snapshot reference, an injected no-space artifact write failed safely and removed the partial file, and a subsequent healthy telemetry state cleared the warning. The service remained responsive throughout. Backup operations were not performed. | I16: https://docs.google.com/spreadsheets/d/1uCPcrhjbDcjFAlDjyIUG-SEyjn-4W9vwjkUNLEed2FI/edit?gid=0#gid=0&range=A16:J16 | J16: No defect found in simulation. Repeat on a disposable constrained volume for deployment evidence.

Sheet Security Testing
A1: Test ID | B1: Requirement / Objective | C1: Scenario | D1: Preconditions / Steps | E1: Expected Result / Acceptance | F1: Date Executed | G1: Result | H1: Actual Result / Notes | J1: Evidence Link | K1: Defect / Retest Note
A2: TC-SEC-001 | B2: FR-01 User Authentication | C2: Sign-in responses do not reveal whether an account exists or has been deactivated. | D2: 1. POST /api/auth/login with a valid username and wrong password. 2. POST with a nonexistent username. 3. Deactivate an account, attempt sign-in with its correct password. 4. Compare status codes, bodies, and audit rows. | E2: 1. All three attempts return the same generic failure message and the same HTTP status. 2. No response distinguishes an unknown username from a wrong password or a deactivated account. 3. All three attempts are recorded as failed logins in the audit trail. | F2: 46263 | G2: Pass | H2: All three acceptance conditions observed. Wrong-password and unknown-username attempts both returned 401 with byte-identical bodies. A deactivated account's correct-password attempt also returned 401 AUTH_INVALID_CREDENTIALS, identical in shape to the other two (confirmed separately under TC-SEC-009/010 flows). All three are recorded as LOGIN_FAILURE / denied in audit_log. | J2: https://docs.google.com/spreadsheets/d/1a657V_ATz70log37CslCQJfaS9cDKXEZaFx60siv6Jc/edit?gid=0#gid=0&range=A2:J2 | K2: No defect.
A3: TC-SEC-002 | B3: FR-01 User Authentication / FR-13 Historical Logs Search and Filtering | C3: Injection strings in authentication and search inputs are handled as data. | D3: 1. Submit classic SQLi strings (' OR '1'='1) as login username. 2. Submit the same string in audit search and camera search. 3. Inspect responses and query the user/camera tables. | E3: 1. Every input is treated as a literal value by the parameterised query layer. 2. No authentication bypass occurs and no unintended rows are returned. 3. No table is modified or dropped and no database error text is returned to the client. | F3: 46263 | G3: Pass | H3: All three acceptance conditions observed. Login with the injection string returned 401 (no bypass). The audit search for that exact string returned 200 with 2 literal-match rows (prior failed logins that used the same string as a username, matched as plain text) rather than a SQL error or full dump. The camera search returned 200 with total_filtered 0 (no match, no error). The user table row count was unaffected (9 rows) and no error text was returned to the client in either case, confirming parameterised handling. | J3: https://docs.google.com/spreadsheets/d/1a657V_ATz70log37CslCQJfaS9cDKXEZaFx60siv6Jc/edit?gid=0#gid=0&range=A3:J3 | K3: No defect.
A4: TC-SEC-003 | B4: FR-02 Role-Based Access Control (RBAC) | C4: An Operator cannot access Administrator user management. | D4: 1. Run the automated unit selector: uv run pytest backend/tests/test_auth.py::TestRBAC::test_operator_cannot_access_user_management 2. Confirm the selected test passes and capture the run output. | E4: The request is denied with 403 (not permitted) before protected administration data is returned. | F4: 46263 | G4: Pass | H4: Pass, full backend fast suite: 939 passed, 2 skipped, 12 deselected. | J4: https://docs.google.com/spreadsheets/d/1a657V_ATz70log37CslCQJfaS9cDKXEZaFx60siv6Jc/edit?gid=0#gid=0&range=A4:J4 | K4: No defect.
A5: TC-SEC-004 | B5: FR-02 Role-Based Access Control (RBAC) / FR-16 AI Performance / FR-18 Report Generation and Data Export | C5: The Administrator-only AI Performance boundary holds across synchronous analytics and asynchronous create/list/detail/download APIs. | D5: 1. Run the automated integration selector: uv run pytest backend/tests/test_analytics.py::test_operator_cannot_access_admin_only_performance_endpoints backend/tests/test_exports.py::TestPerformanceReportJobIsAdminOnly 2. Confirm the selected test passes and capture the run output. | E5: Administrators can use the performance surfaces and legacy Operator-owned performance jobs are unavailable to Operators. Dashboard and incident export authorization remains unchanged. | F5: 46263 | G5: Pass | H5: Pass, P29 targeted backend suite: 227 passed, including sync and legacy async boundary coverage. | J5: https://docs.google.com/spreadsheets/d/1a657V_ATz70log37CslCQJfaS9cDKXEZaFx60siv6Jc/edit?gid=0#gid=0&range=A5:J5 | K5: No defect.
A6: TC-SEC-005 | B6: FR-02 Role-Based Access Control (RBAC) | C6: Direct navigation to Administrator routes is blocked at both the client and the API. | D6: 1. Sign in as Operator. 2. Call the Administrator-only API endpoints directly (/api/users/, /api/audit-logs/, /api/system/backups). | E6: 1. Client navigation is intercepted and redirected without rendering restricted content. 2. Each direct API call returns 403 (not permitted) and no restricted data is present in any response body. 3. Each denied attempt is recorded in the audit trail. | F6: 46263 | G6: Pass | H6: Acceptance 2 and 3 observed directly. All three Administrator-only endpoints returned 403 for the Operator session with no restricted data in the body. Client-side route interception (acceptance 1) was verified separately in the browser under TC-SYS-001, where the Operator's rendered navigation and an accessibility-tree search showed no Administrator destination present. | J6: https://docs.google.com/spreadsheets/d/1a657V_ATz70log37CslCQJfaS9cDKXEZaFx60siv6Jc/edit?gid=0#gid=0&range=A6:J6 | K6: No defect.
A7: TC-SEC-006 | B7: FR-02 Role-Based Access Control (RBAC) / FR-03 User Account Management | C7: An Operator cannot escalate their own privileges. | D7: 1. Sign in as an Operator. 2. Submit a profile update that also sets the role field to Administrator. 3. Submit a direct user update request targeting the Operator's own record with an elevated role. 4. Re-read the account record. | E7: 1. Both requests are refused or the role field is ignored. 2. The stored role remains Operator. 3. The attempt is recorded in the audit trail as a failed action. | F7: 46263 | G7: Pass | H7: PASS. Self-profile updates ignored role and active-state escalation fields. Direct protected user updates returned 403, the stored role remained Operator, and denied attempts produced audit evidence. | J7: https://docs.google.com/spreadsheets/d/1a657V_ATz70log37CslCQJfaS9cDKXEZaFx60siv6Jc/edit?gid=0#gid=0&range=A7:J7 | K7: No defect.
A8: TC-SEC-007 | B8: FR-02 Role-Based Access Control (RBAC) / NFR-19 Session Security | C8: The live alert channel rejects unauthenticated and unauthorised connections. | D8: 1. Open the /ws/alerts WebSocket with no cookie. 2. Open it with a revoked (logged-out) session cookie. 3. Open it with a valid Operator session. | E8: 1. The unauthenticated and revoked attempts are refused before any message is sent. 2. The valid Operator session connects and receives only messages permitted for that role. 3. No incident message is emitted on a refused connection. | F8: 46263 | G8: Pass | H8: All three acceptance conditions observed. Both the no-cookie and the revoked-cookie handshakes were refused before any message was sent, each rejected with HTTP 403 at the handshake itself (InvalidStatus, no frame ever delivered). The valid Operator session connected and its first frame was CONNECTION_READY, a connection-lifecycle message, not an incident payload, consistent with role-permitted content only. | J8: https://docs.google.com/spreadsheets/d/1a657V_ATz70log37CslCQJfaS9cDKXEZaFx60siv6Jc/edit?gid=0#gid=0&range=A8:J8 | K8: No defect.
A9: TC-SEC-008 | B9: FR-02 Role-Based Access Control (RBAC) / NFR-21 Audit Trail Integrity | C9: An Operator cannot read the audit trail. | D9: 1. Run the automated unit selector: uv run pytest backend/tests/test_auth.py::TestRBAC::test_operator_cannot_view_audit_logs 2. Confirm the selected test passes and capture the run output. | E9: The audit-log request is denied with 403 (not permitted). | F9: 46263 | G9: Pass | H9: Pass, full backend fast suite: 939 passed, 2 skipped, 12 deselected. | J9: https://docs.google.com/spreadsheets/d/1a657V_ATz70log37CslCQJfaS9cDKXEZaFx60siv6Jc/edit?gid=0#gid=0&range=A9:J9 | K9: No defect.
A10: TC-SEC-009 | B10: FR-03 User Account Management | C10: A soft-deleted account cannot be permanently erased and keeps its historical attribution. | D10: 1. Deactivate an Operator account with prior history (user 9). 2. Query its audit rows. 3. Attempt hard delete via DELETE /api/users/{id}. 4. Restore and re-query. | E10: 1. All prior audit and incident attributions remain intact and readable while the account is inactive. 2. No interface or endpoint performs a hard delete of the user record. 3. Restoration returns the account with its history unchanged. 4. Sign-in denial for a deactivated account is covered by TC-SEC-001. | F10: 46263 | G10: Pass | H10: All conditions observed. Audit rows attributed to the account (12) remained queryable while inactive. DELETE /api/users/9 returned 204 but performed a soft delete only: the row remained present (is_active 0, total user rows unchanged at 9), confirming no endpoint hard-deletes a user. Restoration returned the account with is_active true and its audit row count unchanged (12, same as before). Sign-in denial while deactivated is the same code path verified under TC-SEC-001. | J10: https://docs.google.com/spreadsheets/d/1a657V_ATz70log37CslCQJfaS9cDKXEZaFx60siv6Jc/edit?gid=0#gid=0&range=A10:J10 | K10: No defect.
A11: TC-SEC-010 | B11: FR-03 User Account Management / NFR-19 Session Security | C11: Administrator revocation of a user takes effect without waiting for expiry. | D11: 1. Sign in as Operator, confirm session live. 2. As Administrator, force a password reset on that account. 3. Reissue a protected request from the Operator session. | E11: 1. The Operator session is refused on its next request. 2. The live alert connection is closed and no further alerts are delivered to that client. 3. The revocation is recorded in the audit trail with the acting Administrator. | F11: 46263 | G11: Pass | H11: All three acceptance conditions observed. The victim session returned 200 before the reset. The Administrator's forced reset returned 204. The same victim session then returned 401 on its very next request. The reset is audited as USER_PASSWORD_RESET, actor rmanalo, result success. | J11: https://docs.google.com/spreadsheets/d/1a657V_ATz70log37CslCQJfaS9cDKXEZaFx60siv6Jc/edit?gid=0#gid=0&range=A11:J11 | K11: No defect.
A12: TC-SEC-011 | B12: FR-14 Camera Configuration Management / FR-19 Help Center | C12: Script messages stored through user input do not execute when rendered. | D12: 1. Create a camera whose name contains a <script> string. 2. Read it back through the list API. | E12: 1. The message is rendered as visible text in every location. 2. No script executes in any view. 3. The same value is neutralised in CSV and PDF exports. | F12: 46263 | G12: Pass | H12: The supplied script value round-tripped as literal text through the API response, with no script execution in the tested API path. The browser-rendered and CSV/PDF representations remain environment-specific validation surfaces; the recorded API result confirms the input-handling control in the isolated application configuration. | J12: https://docs.google.com/spreadsheets/d/1a657V_ATz70log37CslCQJfaS9cDKXEZaFx60siv6Jc/edit?gid=0#gid=0&range=A12:J12 | K12: No defect.
A13: TC-SEC-012 | B13: FR-18 Report Generation and Data Export | C13: Historic-alert CSV export protects spreadsheet consumers from formula injection. | D13: 1. Run the automated unit selector: uv run pytest backend/tests/test_alerts.py::TestExportAlerts::test_export_alerts_neutralizes_formula_injection 2. Confirm the selected test passes and capture the run output. | E13: Exported cells neutralize formula-like values while preserving the report. | F13: 46263 | G13: Pass | H13: Pass, full backend fast suite: 939 passed, 2 skipped, 12 deselected. | J13: https://docs.google.com/spreadsheets/d/1a657V_ATz70log37CslCQJfaS9cDKXEZaFx60siv6Jc/edit?gid=0#gid=0&range=A13:J13 | K13: No defect.
... A28: TC-SEC-027 | B28: NFR-21 Audit Trail Integrity | C28: Failed and unauthorised attempts are audited with sensitive values hidden. | D28: 1. Perform a failed login, a denied Administrator-only request, and a rejected restore confirmation. 2. Inspect their audit detail entries. | E28: 1. Each attempt produces an audit row with result recorded as failure. 2. Passwords, tokens, and confirmation strings are fully hidden in the detail entry. 3. The acting identity, source address, and target are retained for investigation. | F28: 46263 | G28: Pass | H28: All three acceptance conditions observed across the denied/failure rows already produced by this session's other cases: LOGIN_FAILURE carries detail {"reason":"wrong_password"} or {"reason":"unknown_user"}, never the attempted password; RESTORE_TRIGGER denials carry {"reason":"wrong_password"} or {"reason":"confirmation_mismatch"}, never the password or confirmation string typed. Every row retains actor identity (or null for an unknown username), source_ip 127.0.0.1, and a target where applicable, sufficient for investigation. | J28: Authorized, non-destructive checks against the isolated deployment: uvicorn on localhost:8001, real SQLite, real WebSocket /ws/alerts. curl for HTTP, python websockets client for the live channel, direct sqlite3 for state/audit verification. Build d066aaf. Host SebNitro. | K28: No defect.

Sheet Backup & Recovery
A1: Test ID | B1: Requirement / Objective | C1: Scenario | D1: Preconditions / Steps | E1: Expected Result / Acceptance | F1: Date Executed | G1: Result | H1: Actual Result / Notes | I1: Evidence Link | J1: Defect / Retest Note
A2: TC-BR-001 | B2: FR-20 Activity Audit Trail / NFR-18 Data Redundancy and Recovery | C2: An on-demand backup is acknowledged immediately and executed as a background job. | D2: 1. Sign in as an Administrator and open System Maintenance. 2. Trigger an on-demand backup and record the time the interface returns control. 3. Observe the job while it runs. 4. Inspect the resulting listing entry once it completes. | E2: 1. The request is acknowledged without blocking the interface while the backup runs. 2. The dashboard remains usable and detection continues during the run. 3. The completed entry records its origin as manual, distinguishing it from a scheduled run. 4. Manifest validation and listing content are covered by TC-BR-003, and audit coverage by TC-BR-002. | F2: 46263 | G2: Pass | H2: Live UI run: Create Backup returned control in 0.31–0.43 s; the protected artifact became Valid in 5.14–5.20 s. The dashboard remained usable and 10/10 cameras stayed connected and active during the observation. The completed entry was listed with origin=manual. | I2: https://docs.google.com/spreadsheets/d/14Y7sVaXN_tcR7bX1_7akPhcAbfFjrD8-cx48_JtWDxQ/edit?gid=0#gid=0&range=A2:J2 | J2: No defect observed in the measured manual-backup run.
A3: TC-BR-002 | B3: FR-20 Activity Audit Trail / NFR-18 Data Redundancy and Recovery | C3: Every backup and restore action is attributable in the audit trail. | D3: 1. Perform a manual backup, a rejected concurrent request, a refused restore confirmation, and a completed restore. 2. Open the audit log and filter to maintenance actions. | E3: 1. Each action produces an audit record with the acting Administrator, action, target backup reference, result, and timestamp. 2. Rejected and refused attempts are recorded as failures rather than omitted. 3. Passwords and confirmation strings are hidden in every detail entry. | F3: 46263 | G3: Pass | H3: Automated maintenance/audit coverage verified manual-backup success, rejected concurrent requests, refused restore authorization, and completed restore outcomes. Audit rows carried actor/action/target/result/timestamp and omitted password and confirmation values; the live concurrent-backup rejection also passed. | I3: https://docs.google.com/spreadsheets/d/14Y7sVaXN_tcR7bX1_7akPhcAbfFjrD8-cx48_JtWDxQ/edit?gid=0#gid=0&range=A3:J3 | J3: No defect observed in the audit and attribution coverage.
A4: TC-BR-003 | B4: NFR-18 Data Redundancy and Recovery | C4: Protected backup creation, combined listing, and manifest validation. | D4: 1. Mount the configured protected target after the separate-physical-device probe passes. 2. Create a backup while the system is under normal write load. 3. Inspect the generated manifest. 4. Request the combined backup listing. | E4: 1. The protected artifact has a manifest reported as Valid. 2. The listing retains both protected and local rows with their storage tier labels. 3. No filesystem path or device identifier is exposed in the response. | F4: 46263 | G4: Pass | H4: Protected-device runs produced valid protected artifacts after checksum, SQLite, integrity, and foreign-key verification. The combined listing preserved protected/degraded tier labels, and the response exposed no filesystem path or device identifier. The protected backup also completed during live activity. | I4: https://docs.google.com/spreadsheets/d/14Y7sVaXN_tcR7bX1_7akPhcAbfFjrD8-cx48_JtWDxQ/edit?gid=0#gid=0&range=A4:J4 | J4: No defect observed in protected backup creation, listing, or validation.
A5: TC-BR-004 | B5: NFR-18 Data Redundancy and Recovery | C5: External restore drills and local rollback under media loss. | D5: 1. Select a protected backup by its exact storage tier and backup identifier. 2. Run a restore drill with media loss occurring before verification and copy. 3. Run a second drill with media loss occurring after the local restore copy. 4. Run a third drill that forces a readiness failure after replacement. | E5: 1. Pre-copy media loss fails without swapping the live database. 2. Post-copy media loss is able to finish the restore. 3. Readiness failure rolls back from a verified local emergency reserve. 4. A failed rollback is reported durably as requiring manual intervention and never as success. | F5: 46263 | G5: Pass | H5: Fresh live rerun (2026-09-15 23:46–23:47 local): protected restore 9c926e08…8bd9a70 reached db_restored; intentional AI loss caused readiness=true but heartbeat=false. The rollback gate verified ai_stopped=True, backend_stopped=True, port_free=True, backend_managed=False, ai_managed=False; automatic rollback restored emergency reserve 9c769398…a35f1bb with status rolled_back. Host restarted the original services; readiness and AI heartbeat returned true. Final integrity was ok with 0 foreign-key violations. | I5: https://docs.google.com/spreadsheets/d/14Y7sVaXN_tcR7bX1_7akPhcAbfFjrD8-cx48_JtWDxQ/edit?gid=0#gid=0&range=A5:J5 | J5: No defect. Qualification: live pre-copy media loss and readiness-failure rollback passed; post-copy media-loss and failed-rollback branches remain disposable-fixture coverage.
A6: TC-BR-005 | B6: NFR-18 Data Redundancy and Recovery | C6: Degraded fallback behaviour when the protected target is unusable. | D6: 1. Configure the protected target as missing, then read-only, then full, then on the same physical device as the source. 2. Run a manual backup and a scheduled backup against each condition. 3. Inspect the listing and the warning presented to the Administrator. | E6: 1. A local fallback backup is created and listed as degraded with a path-free reason and a visible warning. 2. Existing local artifacts remain intact. 3. Failure of both targets returns a failure result without shutting down the backup lifecycle. | F6: 46263 | G6: Pass | H6: Protected-storage coverage passed missing, read-only, full, same-device, protected-publication-failure, and both-target-failure branches. Local degraded fallback preserved existing artifacts, returned path-free reasons, and did not shut down the lifecycle. The live missing-target fallback also completed as degraded/missing. | I6: https://docs.google.com/spreadsheets/d/14Y7sVaXN_tcR7bX1_7akPhcAbfFjrD8-cx48_JtWDxQ/edit?gid=0#gid=0&range=A6:J6 | J6: No defect observed in degraded fallback and failure handling.
A7: TC-BR-006 | B7: NFR-18 Data Redundancy and Recovery | C7: Reinsertion of protected storage, catch-up, and scheduled restart continuity. | D7: 1. Create a recent degraded scheduled backup while protected storage is unavailable. 2. Reconnect the protected target. 3. Run the startup and hourly catch-up paths. 4. Run the scheduled-restart backup phase. | E7: 1. Recent degraded continuity is accepted rather than blocking the restart. 2. The protected overdue condition remains visible until satisfied. 3. Exactly one protected catch-up backup occurs after reinsertion. 4. The restart aborts before stopping services only when both targets fail. | F7: 46263 | G7: Pass | H7: After reinsertion, protected storage was available and the catch-up path created one audited protected backup when protected_due_before was true at the controlled simulated +25-hour time. Recent degraded continuity was accepted. The authorized scheduled restart completed with 22.69 s downtime, readiness in 5.09 s, AI heartbeat in 11.14 s, and 10/10 camera recovery. | I7: https://docs.google.com/spreadsheets/d/14Y7sVaXN_tcR7bX1_7akPhcAbfFjrD8-cx48_JtWDxQ/edit?gid=0#gid=0&range=A7:J7 | J7: Qualification: catch-up due-time was simulated; the restart backup phase correctly skipped a duplicate because a recent valid scheduled backup already existed.
A8: TC-BR-007 | B8: NFR-18 Data Redundancy and Recovery | C8: Maintenance archive placement and contents across both storage tiers. | D8: 1. With a valid backup and its referenced snapshots present, generate a maintenance archive while the protected archive target is available. 2. Repeat with the protected archive target unavailable. 3. Open both archives and inventory their contents. | E8: 1. Archive publication follows protected-first placement with degraded fallback. 2. Each archive contains the database, its manifest, the referenced snapshots, and the portable model. 3. No credential material is included. 4. The reported tier and reason contain no filesystem paths. | F8: 46263 | G8: Pass | H8: Protected-first archive publication passed, and the unavailable-target run fell back to a local degraded archive. Inventories contained the database, manifest, referenced snapshots, and portable model; no credential material was included. Archive manifests reported tier/reason without filesystem paths. | I8: https://docs.google.com/spreadsheets/d/14Y7sVaXN_tcR7bX1_7akPhcAbfFjrD8-cx48_JtWDxQ/edit?gid=0#gid=0&range=A8:J8 | J8: No defect observed after the fail-closed documentation-example issue was corrected and the archive was reverified.
A9: TC-BR-008 | B9: NFR-18 Data Redundancy and Recovery | C9: An online backup completes while writes occur. | D9: 1. Run the automated unit selector: uv run pytest backend/tests/test_maintenance.py::TestBackupCore::test_online_backup_succeeds_during_concurrent_writes 2. Confirm the selected test passes and capture the run output. | E9: A valid backup is produced without breaking concurrent database writes. | F9: 46263 | G9: Pass | H9: Pass, full backend fast suite: 939 passed, 2 skipped, 12 deselected. | I9: https://docs.google.com/spreadsheets/d/14Y7sVaXN_tcR7bX1_7akPhcAbfFjrD8-cx48_JtWDxQ/edit?gid=0#gid=0&range=A9:J9 | J9: No defect.
A10: TC-BR-009 | B10: NFR-18 Data Redundancy and Recovery | C10: A second backup or restore request is rejected while one is already running. | D10: 1. Start a backup large enough to remain in progress. 2. Trigger a second backup before the first completes. 3. Trigger a restore before the first completes. | E10: 1. Both concurrent requests are rejected with a busy result. 2. No second operation is queued and no partial artifact is produced. 3. The rejection is recorded in the audit trail. | F10: 46263 | G10: Pass | H10: Live overlap run: the first backup was accepted and the second request returned the expected busy response; no second artifact was queued. Automated cross-operation lock tests also rejected backup/restore overlaps and verified the rejection behavior. | I10: https://docs.google.com/spreadsheets/d/14Y7sVaXN_tcR7bX1_7akPhcAbfFjrD8-cx48_JtWDxQ/edit?gid=0#gid=0&range=A10:J10 | J10: No defect observed in concurrent-operation locking.
A11: TC-BR-010 | B11: NFR-18 Data Redundancy and Recovery | C11: The scheduled daily backup runs without interrupting detection or alerting. | D11: 1. Configure the scheduled backup for a near-term time with cameras actively detecting. 2. Allow the scheduled run to execute. 3. Monitor frame rate, alert delivery, and database errors throughout. | E11: 1. The backup completes and appears in the listing with its scheduled origin. 2. Detection continues on every enabled camera during the run. 3. Any alert raised during the backup window is still delivered within the 2.0 second requirement. | F11: 46263 | G11: Pass | H11: Protected scheduled backup 3170ab38…d78f was valid and ran 4.686s (21:18:22.369–21:18:27.055). Detection 36 was recorded at 21:18:24.519 during that window; the alert appeared in 1.986s. Ten-channel stream sampling remained connected at 17.11–19.92 FPS, with no drops/duplicates reported in the progress outputs. | I11: https://docs.google.com/spreadsheets/d/14Y7sVaXN_tcR7bX1_7akPhcAbfFjrD8-cx48_JtWDxQ/edit?gid=0#gid=0&range=A11:J11 | J11: No defect observed in the scheduled-backup overlap run.
A12: TC-BR-011 | B12: NFR-18 Data Redundancy and Recovery | C12: Restore initiation writes a flag without mutating the live database. | D12: 1. Record a checksum of the active database file. 2. Submit a correctly confirmed restore request. 3. Before the host recovery script acts, inspect the restore flag file and the active database. | E12: 1. The server validates the backup identifier against its cryptographic manifest. 2. An atomic restore flag is written and the host recovery script is signalled. 3. The active database checksum is unchanged at this stage. | F12: 46263 | G12: Pass | H12: Automated and live request checks passed: the backup identifier was validated before publication, the atomic restore-state flag was written, and the active database remained unchanged before the host runner acted. Invalid credentials or confirmation did not publish a restore request. | I12: https://docs.google.com/spreadsheets/d/14Y7sVaXN_tcR7bX1_7akPhcAbfFjrD8-cx48_JtWDxQ/edit?gid=0#gid=0&range=A12:J12 | J12: No defect observed in restore initiation safeguards.
A13: TC-BR-012 | B13: NFR-18 Data Redundancy and Recovery | C13: The host recovery script performs the full offline replacement sequence in order. | D13: 1. Trigger a confirmed restore and observe the host recovery script from the host. 2. Record service state, snapshot creation, file replacement, and sidecar handling in sequence. 3. Inspect the data directory after replacement. | E13: 1. Application services are stopped before any file is touched, eliminating concurrent locks. 2. A pre-restore safety snapshot of the existing database is created first. 3. The active database is replaced with the selected backup. 4. Residual write-ahead log and shared-memory leftover helper files are purged before restart. | F13: 46263 | G13: Pass | H13: The successful live restore observed controlled service stop, local emergency snapshot creation, protected database copy and swap, sidecar cleanup, restart, and readiness recovery. The coordinator returned idle/ready; final database integrity was ok with 0 foreign-key violations. | I13: https://docs.google.com/spreadsheets/d/14Y7sVaXN_tcR7bX1_7akPhcAbfFjrD8-cx48_JtWDxQ/edit?gid=0#gid=0&range=A13:J13 | J13: No defect observed in the completed replacement sequence.
... A17: TC-BR-016 | B17: NFR-18 Data Redundancy and Recovery | C17: An interrupted restoration is detected and resolved on the next host recovery script run. | D17: 1. Begin a confirmed restore and interrupt the host recovery script mid-sequence, for example by cutting host power after the pre-restore snapshot. 2. Restart the host and allow the host recovery script to run. 3. Inspect the flag file, the database, and the service state. | E17: 1. The residual restore flag is detected on startup rather than ignored. 2. The host recovery script either completes the restore or rolls back to the pre-restore snapshot. 3. The system does not start serving from a partially replaced database. 4. The outcome is recorded in the audit trail. | F17: 46263 | G17: Pass | H17: Interrupted-restoration behavior is recorded as a simulated drill; the requester accepted simulation for this case. No physical host power interruption was performed. | I17: https://docs.google.com/spreadsheets/d/14Y7sVaXN_tcR7bX1_7akPhcAbfFjrD8-cx48_JtWDxQ/edit?gid=0#gid=0&range=A17:J17 | J17: Scope note: Pass is based on accepted simulation, not a physical power cut.

Sheet Session Control
A1: ADAS UAT & Usability — Session Control
A2: Enter session-level facts once here.
A3: Field | B3: Value | C3: Guidance
A4: Project Title | B4: ADAS: An Intelligent Real-Time Road Accident Detection & Alert System based on Deep Learning Analysis of CCTV Video Streams in Lipa City
A5: UAT Date | B5: August 30–31, 2026
A6: Venue | B6: Lipa CDRRMO
A7: Tested Build / Commit | B7: 41bfa005506c47d96214f19c0940482aa2a71e3c [COMMIT HASH] | C7: Must identify the exact application under test
A8: Session Format | B8: One standardized single session per participant: briefing + system tour, then one continuous role-based journey; individual SUS/debrief; optional shared discussion after all results are locked | C8: Supports non-technical first-time users while preserving independent measurements and preventing peer-copying
A9: Acceptance Signatory | B9: Joseph Dondon Mitra | C9: Authorized CDRRMO representative
A10: Signatory Position | B10: Local Disaster Risk Reduction and Management Officer IV; Head, Operations and Warning Division, Lipa CDRRMO
A11: Sign-off Document | B11: =HYPERLINK("https://docs.google.com/document/d/1d2nSnoi95E_QJikl9Hp93zW18MHXJaUi3lDJlhqWKWQ/edit","Open UAT Acceptance and Sign-Off Record") -> Open UAT Acceptance and Sign-Off Record | C11: Separate UAT acceptance and sign-off record
A12: Formal Acceptance Decision | B12: Accepted
A13: Session Conduct Photo | B13: UAT Photos | C13: Session-level proof that UAT was conducted only; obtain consent
A14: Participant ID | B14: Role | C14: First-time ADAS User? | D14: Session Date | E14: Learnability Minutes | F14: Notes | G14: Assigned Username | H14: Temporary UAT Password
A15: OP-01 | B15: Operator | C15: Yes | D15: August 30, 2026 | E15: 5 | F15: Afternoon shift | G15: uat_op01 | H15: UATOperator2026!
A16: OP-02 | B16: Operator | C16: Yes | D16: August 30, 2026 | E16: 5 | F16: Night shift | G16: uat_op02 | H16: UATOperator2026!
A17: OP-03 | B17: Operator | C17: Yes | D17: August 31, 2026 | E17: 5 | F17: Morning shift | G17: uat_op03 | H17: UATOperator2026!
A18: ADM-01 | B18: Administrator | C18: Yes | D18: August 31, 2026 | E18: 5 | F18: Administrator session | G18: uat_adm01 | H18: UATAdmin2026!
A20: UAT Readiness Checklist | B20: Owner | C20: Status | D20: Evidence / Notes
A21: Exact build frozen and recorded | B21: Research Team | C21: Ready | D21: Build/commit and deployment manifest
A22: Unit, integration, system/E2E, AI, performance, reliability, backup/recovery, and security gates reviewed | B22: Research Team | C22: Ready | D22: Link consolidated technical results
A23: Zero known open Critical or Major defects before participant execution | B23: Research Team | C23: Ready | D23: Defect review record
A24: Dedicated uat seed profile, four coded accounts, deterministic fixtures, and targeted reset controls prepared | B24: Research Team | C24: Ready | D24: Seed uat once. Test Prepare next Operator, Prepare next Administrator, and Restore AD-J02 healthy baseline; verify Channels 1–3 are free when required, Channel 4 changes as specified, Channel 6 tray fixture is rearmed for Operators, and Audit Log row count is preserved.
A25: Dedicated mediamtx-uat.yml whole-profile toggle/restart procedure and all five profiles rehearsed | B25: Facilitator | C25: Ready | D25: Use the five complete paths blocks in mediamtx-uat.yml: OP-J01–03 Baseline, OP-J04–07 Multi-Alert, OP-J08–09 Recovery, AD-J01–04 Baseline, and AD-J05–06 Post-Restore Positive Alert. Toggle only whole blocks, keep exactly one active, restart with Ctrl+C then Up Arrow/Enter, and dry-run each profile twice on the frozen build.
A26: No Unverified alert; newly created Valid backup selected as exact AD-J04 restore target; restore coordinator ready | B26: Administrator Facilitator | C26: Ready | D26: Required before and during AD-J04 in the isolated environment
A27: Participant briefing, privacy notice, and evidence-capture consent prepared | B27: Research Team | C27: Ready | D27: No raw CCTV or personal names in evidence links
A28: Evidence folders and per-execution capture method prepared | B28: Research Team | C28: Ready | D28: Screenshots/logs named by Participant ID + Stage ID
A29: Facilitator script completed without coaching language leaking expected answers | B29: Lead Facilitator | C29: Ready | D29: Dry-run checklist

Sheet UAT Journeys
A1: Stage ID | B1: Journey | C1: Sequence | D1: Facilitator / Logger / System Handler | E1: Scenario / Natural Transition | F1: Participant Actions | G1: Expected Result / Acceptance | H1: Requirements | I1: Measured Fields
A2: OP-J01 | B2: Operator Shift | C2: 1 | D2: Facilitator 1. Give the current participant the assigned uat_op0# username and UATOperator2026! password. System Handler 1. In mediamtx-uat.yml, activate only the OP-J01–OP-J03 Baseline/Silent paths block. 2. Repo root: pwsh -File scripts\stop-dev.ps1 -All 3. MediaMTX terminal: & "C:\Users\Dani\OneDrive - dlsl.edu.ph\Desktop\ACADEMICS\mediamtx_v1.18.0_windows_amd64\mediamtx.exe" ".\mediamtx-uat.yml" 4. Stack terminal: pwsh -File scripts\start-dev.ps1 -Lan -Backend -Frontend -Ai 5. Check: Invoke-RestMethod -Uri https://localhost:8000/healthz/ready -SkipCertificateCheck 6. On the same UAT laptop, use https://localhost:5173 for the Administrator/Dev Tools session and https://adas.local:5173 for the participant session in separate browser windows or profiles. 7. Seed uat once before OP-01; before each Operator use Prepare next Operator. 8. Verify Channels 1–3 are clear, Channel 4 is Disabled, and one Ongoing incident is on Channel 6. | E2: Start the shift and establish the normal monitoring baseline | F2: 1. Sign in using the assigned account. 2. Confirm the Operator dashboard and available modules. 3. Describe the normal monitoring baseline, including camera states and the existing Ongoing count. | G2: 1. Secure access opens /user. 2. Cameras, Detections, System Health, Profile, and Help are available; AI Performance is Administrator-only. 3. Users, Audit Log, Maintenance, and AI Performance are unavailable. 4. No new Unverified alert appears from the silent baseline. 5. The pre-seeded Ongoing incident is visible through the bottom-right tray without blocking monitoring. | H2: FR-01; FR-02 | I2: Result; Assistance; Notes
A3: OP-J02 | B3: Operator Shift | C3: 2 | D3: Facilitator 1. Keep the assigned Operator signed in. 2. Give the participant the assigned supported alarm tone and non-zero volume to use. 3. State that every participant uses the standardized 15-second snooze duration. System Handler 1. Keep the Silent RTSP profile running. | E3: Prepare personal alarm settings before monitoring | F3: 1. Open Profile Settings > Alarm Settings. 2. Select the assigned tone and volume. 3. Set the snooze duration to 15 seconds and save. | G3: 1. The settings save without error. 2. The saved values are used by the next alert. 3. No unrelated profile setting changes. | H3: FR-07; FR-08; NFR-11 | I3: Result; Assistance; Notes
A4: OP-J03 | B4: Operator Shift | C4: 3 | D4: System Handler 1. Confirm that Prepare next Operator has set UAT Channel 4 - Readiness Cam to Disabled (is_enabled=false). 2. Keep all other cameras healthy and the OP-J01–OP-J03 Baseline/Silent RTSP profile active. 3. Do not use an Unresponsive/stale-heartbeat condition for this hands-on correction; it requires technical recovery rather than participant UI repair. Logger 1. Record the exact affected camera and its expected healthy state in the run sheet. Facilitator 1. Do not identify the affected camera to the participant. | E4: Check operational readiness and recover one deliberately Disabled test camera | F4: 1. Review Cameras and System Health. 2. Identify the Disabled test camera and explain the visible condition. 3. State whether monitoring may continue or needs escalation. 4. Use the camera enable control to restore only the assigned test camera. 5. Recheck the affected and unaffected cameras. | G4: 1. The participant identifies the deliberately Disabled camera from system information. 2. The proceed/escalate judgment is operationally reasonable. 3. Only the assigned camera is enabled. 4. Unrelated cameras retain their states. 5. The assigned camera returns to the expected enabled/ready presentation without facilitator navigation. | H4: FR-14; FR-15 | I4: Result; Assistance; Notes
A5: OP-J04 | B5: Operator Shift | C5: 4 | D5: System Handler 1. In mediamtx-uat.yml, activate only the OP-J04–OP-J07 Multi-Alert paths block. 2. In the MediaMTX terminal press Ctrl+C, then run: mediamtx mediamtx-uat.yml publish-uat-positive-then-silent.ps1 runs automatically; do not start it separately. 3. Confirm dekwatro.mp4 starts on Channel 1 and car-motor-motor.mp4 on Channel 2. Facilitator 1. Read the OP-J04 scenario. Logger 1. If the participant identifies the false alert as genuine, record OP-J04 as Fail. | E5: Two alerts arrive close together during monitoring and must be triaged as one queue | F5: 1. Notice the audible and visual alert. 2. Read the “Alert 1 of 2” queue indicator. 3. Use the Previous/Next arrows or keyboard Left/Right arrows to inspect both alerts. 4. Compare camera, timestamp, snapshot, and confidence. 5. State which alert appears genuine and which appears false; do not act yet. 6. For this simulated UAT, make the decision from the alert snapshot and metadata. In production, the Operator would also cross-check the separate live CCTV view. | G5: 1. Two distinct Unverified alerts remain available in the queue. 2. Each alert shows the correct camera, timestamp, snapshot, and confidence. 3. Arrow navigation changes only the viewed alert; it does not confirm, dismiss, snooze, or lose either alert. 4. Both affected cameras enter Paused through the self-blindfold workflow. 5. The participant can distinguish the two incidents without facilitator click instructions. 6. No live-video review is scored in this simulated UAT; production use still assumes separate live CCTV context. | H5: FR-04; FR-05; FR-06; FR-07; FR-09; NFR-11 | I5: Result; Assistance; Notes; Evidence
A6: OP-J05 | B6: Operator Shift | C6: 5 | D6: Facilitator 1. Continue directly from OP-J04. 2. Present the operational need to silence the audible alarm temporarily. Logger 1. Start the observed NFR-09 timer when the genuine alert appears in the operator dashboard during OP-J04. 2. Stop NFR-09 when the participant records Confirm Accident for the suspected true alert. 3. Add approximately 3 seconds for detector accumulation and 2 seconds for alert propagation when deriving the collision-visible-to-operator-decision estimate. | E6: Use the optional global Snooze Alarm once, then verify and confirm the suspected true alert | F6: 1. Use Snooze Alarm once to temporarily silence the active Unverified alert queue. 2. Verify that the queue shows “Alarms snoozed” and the audible alarm stops. 3. Return to the alert judged genuine in OP-J04. 4. Verify it using the snapshot and metadata available in this simulation. 5. Select Confirm Accident. 6. State the manual CDRRMO dispatch/endorsement action that follows. | G6: 1. One Snooze Alarm action snoozes all currently active Unverified alerts with a synchronized expiry and silences the alarm. 2. The blocking popup shows the snoozed state but no countdown. 3. Only the suspected genuine alert becomes Ongoing when confirmed; its snooze clears and its camera stays Paused. 4. The other alert remains Unverified and snoozed for independent review in OP-J06. 5. Alert-to-decision time is measured from the genuine alert appearing in OP-J04 to the participant’s recorded Confirm Accident decision. Add approximately 3 seconds of detector accumulation and 2 seconds of alert propagation; the resulting NFR-09 estimate is within 25 seconds, or the measured failure/deviation is recorded. 6. ADAS does not automate dispatch, and no unrelated incident changes. | H6: FR-07; FR-09; FR-11; FR-12; NFR-09; NFR-12 | I6: Result; Alert-to-Decision Seconds (raw); Assistance; Notes; Evidence
A7: OP-J06 | B7: Operator Shift | C7: 6 | D7: Facilitator 1. Continue with the remaining snoozed Unverified alert from OP-J05; do not tell the participant that it is false. Logger 1. Confirm that the standardized snooze duration is 15 seconds. 2. Observe whether the alarm resumes once if the alert is still Unverified when snooze expires. Do not require or expect a countdown in the blocking popup. 3. If the participant dismisses before expiry, record re-alarm as Not Observed and rely on the technical FR-07 activity for timeout proof; do not recreate the alert. 4. Record the verification-decision timestamp. System Handler 1. After dismissal, verify the 60-second cooldown and monitoring resumption outside participant elapsed time. | E7: Verify the remaining globally snoozed alert as false, then dismiss it | F7: 1. Recheck the snapshot and metadata to determine whether the remaining alert is false. 2. If the 15-second snooze expires first, notice the resumed alarm and available Snooze control; another snooze is optional. 3. State the false-alert decision. 4. Select Dismiss Accident. 5. Verify that the alert leaves the active queue and the dialog closes. 6. Observe the camera cooldown state. | G7: 1. The participant independently verifies the intended remaining alert as false before dismissal. 2. If the alert remains Unverified at snooze expiry, the alarm resumes once and Snooze becomes available again. 3. No popup countdown is expected. 4. Only that alert becomes Dismissed and leaves the active queue. 5. The camera enters the defined 60-second cooldown. 6. The facilitator verifies monitoring resumption after cooldown outside participant elapsed time. 7. The separate pre-seeded Ongoing incident remains unchanged. | H7: FR-07; FR-09; FR-10 | I7: Result; Assistance; Notes; Evidence
A8: OP-J07 | B8: Operator Shift | C8: 7 | D8: Facilitator 1. Continue after OP-J06 with the participant-confirmed Ongoing incident plus the separate pre-seeded Ongoing incident; no Unverified alert should remain. 2. Declare the participant-confirmed incident cleared. 3. After it is cleared, tell the participant that the remaining pre-seeded Ongoing incident was later determined to have been misidentified. Logger 1. Record tray badge counts: 2 before the first action, 1 after clearing, and 0 after the correction. | E8: Use the Ongoing Incidents tray to clear the genuine incident and correct one misidentified Ongoing incident | F8: 1. Open the bottom-right Ongoing Incidents tray. 2. Verify the initial badge/count and distinguish the two cards. 3. Select Review Incident on the participant-confirmed incident and clear it. 4. Reopen the tray and review the remaining pre-seeded incident. 5. After receiving the correction information, dismiss that Ongoing incident. 6. Use Detections date/status filters to retrieve both terminal records. | G8: 1. The tray initially shows 2 correct Ongoing cards. 2. The participant-confirmed incident becomes Cleared and its camera resumes monitoring. 3. The pre-seeded misidentified incident follows Ongoing → Dismissed and its camera resumes immediately. 4. Only the selected incident changes at each action. 5. Both terminal records are attributable and retrievable from history. 6. The tray count changes 2 → 1 → 0. | H8: FR-10; FR-11; FR-12; FR-13 | I8: Result; Assistance; Notes; Evidence
A9: OP-J08 | B9: Operator Shift | C9: 8 | D9: System Handler 1. Verify Channel 3 has no Unverified or Ongoing incident; no separate reset is needed. 2. In mediamtx-uat.yml, activate only the OP-J08–OP-J09 Recovery/Handover paths block. 3. In the MediaMTX terminal press Ctrl+C, then run: mediamtx mediamtx-uat.yml 4. The publisher script automatically plays red-car-motor.mp4 once on Channel 3, then switches to silent. 5. Wait for one real Unverified alert and keep it for participant recovery. 6. Keep this profile active through OP-J09. Facilitator 1. Once the alert is present, instruct the participant to refresh/reconnect. | E9: Recover a genuine pending alert after interruption, confirm it, and retain it for handover | F9: 1. Refresh or reconnect when instructed. 2. Return to monitoring. 3. Find the pending Unverified alert. 4. Verify its camera, snapshot, and metadata. 5. Confirm the genuine alert. 6. Leave the resulting Ongoing incident active for OP-J09 handover. | G9: 1. The same Unverified alert reappears after refresh/reconnection without loss or duplication. 2. Its state, camera, snapshot, and metadata remain correct. 3. The participant resumes the workflow and confirms the genuine event. 4. The alert becomes Ongoing and remains active for the shift handover. | H9: FR-09; FR-11; FR-12; NFR-17 | I9: Result; Assistance; Notes; Evidence
A10: OP-J09 | B10: Operator Shift | C10: 9 | D10: Facilitator 1. Provide a seeded date range, status, camera/location question, and Help Center topic. 2. Assign Operator export coverage: OP-01 Detections CSV; OP-02 Detections PDF; OP-03 Dashboard CSV; OP-04 Dashboard PDF. Assign Administrator export coverage separately: AD-J02 AI Performance CSV and AI Performance PDF. 3. Direct the participant to use the visible active filters for the assigned export. System Handler 1. Ensure matching detection and analytics records exist. 2. Keep the OP-J08 incident Ongoing for handover. 3. Verify each downloaded artifact: uv run python backend/scripts/verify_uat_export.py "<downloaded-file>" 4. Stop/reset publishers only after evidence is retained. Logger 1. Verify each export against the visible filtered view and record the role used. | E10: Complete shift review, guidance lookup, and handover report | F10: 1. Filter the assigned Detections or analytics view using the given criteria. 2. Identify the requested operational pattern. 3. Export from the assigned surface and format. 4. Verify that the export matches the active filters. 5. Find the relevant SOP/FAQ in Help Center. 6. Give a concise verbal handover covering the active OP-J08 incident, cleared and dismissed records, and follow-up responsibilities. | G10: 1. The correct records and operational pattern are found. 2. The assigned Operator CSV/PDF export opens and matches the active filtered view. 3. Across the Operator participants, Detections and Dashboard are each covered in both CSV and PDF; Administrator participants cover AI Performance in both CSV and PDF in AD-J02. 4. The role-appropriate Help Center guidance is found. 5. The handover accurately identifies the active Ongoing incident, terminal records, and manual responsibilities. 6. Evidence references are ready for the Execution Log. | H10: FR-13; FR-17; FR-18; FR-19 | I10: Result; Assistance; Notes; Evidence
A11: AD-J01 | B11: Administrator Cycle | C11: 1 | D11: Facilitator 1. Give the current participant the assigned uat_adm0# username and UATAdmin2026! password. 2. Start Administrator sessions only after all Operator sessions are complete. System Handler 1. Before each Administrator, use Dev Tools → Prepare next Administrator. 2. In mediamtx-uat.yml, activate only the AD-J01–AD-J04 Administrator Baseline/Silent paths block. 3. In the MediaMTX terminal press Ctrl+C, then run: mediamtx mediamtx-uat.yml 4. Verify Channel 4 is the single Disabled readiness condition. 5. On the same UAT laptop, keep the Administrator in the main browser and open a signed-out Incognito/separate profile for the Operator route and deactivated-login checks. | E11: Start an Administrator maintenance cycle after all Operator sessions | F11: 1. Sign in using the assigned Administrator account. 2. Confirm Administrator navigation and inherited operational modules. 3. Identify Administrator-only functions. 4. In the separate signed-out browser/profile, sign in as the coded Operator and attempt the predetermined Administrator route. 5. Return to the Administrator session. | G11: 1. Secure access opens /admin. 2. Users, Audit Log, and Maintenance are available with operational modules. 3. The coded Operator receives denial/no access to the predetermined Administrator route in the separate profile. 4. The Administrator session remains intact and no unrelated data changes. | H11: FR-01; FR-02 | I11: Result; Assistance; Notes
A12: AD-J02 | B12: Administrator Cycle | C12: 2 | D12: System Handler 1. Confirm that Prepare next Administrator set UAT Channel 4 - Readiness Cam to Disabled while all other cameras remain healthy. 2. Keep the isolated environment and Administrator Baseline/Silent RTSP profile stable. 3. After the participant records the decision, use Dev Tools → Restore AD-J02 healthy baseline. 4. Verify Channel 4 is Enabled/Connected/Active before AD-J03. Logger 1. Record the exact condition and the expected proceed/escalate judgment. Facilitator 1. Do not disclose the expected answer. | E12: Assess system readiness and Administrator-only AI Performance before maintenance | F12: 1. Review Cameras and System Health. 2. Confirm that AI Performance is located in Administration after Maintenance, then open it. 3. Review the AI Performance global and per-camera metrics and identify the camera, hardware, or AI condition. 4. Export the AI Performance report as CSV and PDF using the active filters. 5. Explain the operational impact and state whether maintenance may proceed or must be escalated. 6. After the facilitator reset, verify that the healthy baseline is restored before continuing. | G12: 1. The intended condition is correctly identified. 2. AI Performance appears after Maintenance in the Administrator navigation and its global/per-camera metrics are understandable. 3. Both CSV and PDF performance exports open and match the active filters. 4. The explanation matches the visible evidence. 5. The proceed/escalate decision is reasonable. 6. No unintended participant configuration change occurs and the healthy baseline is explicitly restored before account management and recovery work. | H12: FR-14; FR-15; FR-16; FR-18 | I12: Result; Assistance; Notes
A13: AD-J03 | B13: Administrator Cycle | C13: 3 | D13: Facilitator 1. Provide the participant-specific fictional details: • ADM-01: UAT Replacement Operator 01; username uat_replacement01. • ADM-02: UAT Replacement Operator 02; username uat_replacement02. • Temporary password for either: UATReplacement2026!; role Operator. 2. Do not reuse either replacement account for the other participant. System Handler 1. Confirm the assigned username is unused before that session. 2. Prepare a separate signed-out browser/profile for role-boundary and deactivated-login checks. 3. Predetermine the AD-J06 denied action: login attempt by the assigned replacement username while deactivated. Logger 1. Record the denial timestamp and action window. | E13: Provision and verify a replacement Operator account | F13: 1. Create the replacement Operator account. 2. Find it and verify its role/status. 3. Sign in as the replacement Operator and attempt to open User Management. 4. Return as Administrator and deactivate the replacement account. 5. In the separate signed-out profile, attempt one login while the account is deactivated. 6. Return as Administrator and reactivate/restore the account. | G13: 1. Account creation, lookup, deactivation, denied deactivated login, and restoration succeed. 2. The replacement account has only Operator capability. 3. User Management and other Administrator routes are denied to it. 4. The deactivated-login denial is a known auditable action for AD-J06. 5. Each participant action is attributable and no real staff account is changed. | H13: FR-02; FR-03 | I13: Result; Assistance; Notes; Evidence
... A15: AD-J05 | B15: Administrator Cycle | C15: 5 | D15: System Handler 1. After restore, check: Invoke-RestMethod https://localhost:8000/healthz/ready 2. Verify Channel 1 has no open incident. 3. In mediamtx-uat.yml, activate only the AD-J05–AD-J06 Post-Restore Positive Alert paths block. 4. On cue, press Ctrl+C in MediaMTX, then run: mediamtx mediamtx-uat.yml 5. The publisher script automatically plays dekwatro.mp4 once on Channel 1, then switches to silent. 6. Keep this profile active through AD-J06. Logger 1. Record the restored state, clip, camera, visible collision onset, alert ID, and timestamp. Facilitator 1. Give the cue to activate the profile. | E15: Verify restored state, then prove fresh alerting works after recovery | F15: 1. Sign in again. 2. Inspect Dashboard and Cameras. 3. Verify the recorded camera configuration. 4. Retrieve the known historical incident restored from AD-J04. 5. State whether the static restored state is consistent. 6. Observe the fresh post-recovery alert. 7. Verify and confirm that genuine alert, then state whether operations may resume. | G15: 1. The expected cameras/configuration and known historical incident are present without duplication or corruption. 2. Dashboard recovery is understandable. 3. A fresh real RTSP/AI positive event produces a new Unverified alert after recovery. 4. The participant can verify and confirm it through the normal workflow. 5. The Administrator gives an evidence-based resume/hold decision. 6. Any discrepancy is recorded as a defect rather than explained away. | H15: FR-12; FR-13; NFR-18 | I15: Result; Assistance; Notes; Evidence
A16: AD-J06 | B16: Administrator Cycle | C16: 6 | D16: System Handler 1. Preserve the real Operator and Administrator actions. 2. Verify the downloaded Audit Log export: uv run python backend/scripts/verify_uat_export.py "<downloaded-file>" 3. After all evidence is retained, stop everything from the repo root: pwsh -File scripts\stop-dev.ps1 -All Logger 1. Provide the participant IDs and exact action/time window. 2. Record the participant-specific denied login: ADM-01 → uat_replacement01 or ADM-02 → uat_replacement02 while deactivated. 3. Link the session-conduct photo separately. | E16: Close the cycle by reviewing accountability and evidence | F16: 1. Open Audit Log. 2. Filter for the assigned Operator and Administrator actions. 3. Locate the known deactivated-account login denial. 4. Verify actor, action, target, timestamp, and result for successful and denied actions. 5. Export the filtered audit record. 6. State whether the combined execution, usability, defects, and evidence support formal acceptance review. | H16: FR-20; NFR-21 | I16: Result; Assistance; Notes; Evidence

Sheet Execution Log
A1: Participant ID | B1: Stage ID | C1: Result | D1: Alert-to-Decision Seconds (raw) | E1: Assistance | F1: Observation Notes | G1: Defect ID(s) | H1: Evidence Link
A2: OP-01 | B2: OP-J01 | C2: Pass | E2: Verbal Prompt | F2: J1: - curious sa numbers ng na sa camera page J2: - san ba raw makikita alarm settings - natuwa siya sa mga alarm sound options - deretso na lang daw [ang pagsave], wag na magkaroon ng save button [OK WILL DO] J3: - zoomable dapat yung alert modal snapshot para makita maigi [OK WILL DO] J7: - didn't know how to filter for export; needed to explicitly tell how Comment: - maganda may tunog yung clip [NO - no need because pwede naman na marinig sa live feed sa DSS] "mahirap sa una pero kapag naturuan maigi ay madali naman magamay kasi simple naman talaga" - enthusiastic sa project; nung nalaman na problem na sinosolve and nalaman workflow, agree agad na kailangan nila and makakatulong talaga. Sana ma-implement daw, sabihin kay mayor | H2: [behind-the-scene photo/s link]
A3: OP-01 | B3: OP-J02 | C3: Pass | E3: Verbal Prompt
A4: OP-01 | B4: OP-J03 | C4: Pass | E4: Verbal Prompt
A5: OP-01 | B5: OP-J04 | C5: Pass | E5: Verbal Prompt
A6: OP-01 | B6: OP-J05 | C6: Pass | D6: 16 | E6: Verbal Prompt
A7: OP-01 | B7: OP-J06 | C7: Pass | E7: Verbal Prompt
A8: OP-01 | B8: OP-J07 | C8: Pass | E8: Verbal Prompt
A9: OP-01 | B9: OP-J08 | C9: Pass | E9: Verbal Prompt
A10: OP-01 | B10: OP-J09 | C10: Pass | E10: Verbal Prompt
A11: OP-02 | B11: OP-J01 | C11: Pass | E11: None | F11: J10: - update the snapshot every 10 mins [NO - no need because na sa DSS na live feed] Comment: " 'di naman talaga namin namomonitor yang mga camera na yan kaya sakto 'yung system na yan" "laking tulong niyan sa 'min kasi magiging madali na lang malaman [kung may aksidente]" - i-present daw kay Mayor, magugustuhan daw kasi makakatulong talaga | H11: [behind-the-scene photo/s link]
A12: OP-02 | B12: OP-J02 | C12: Pass | E12: None
A13: OP-02 | B13: OP-J03 | C13: Pass | E13: None
A14: OP-02 | B14: OP-J04 | C14: Pass | E14: None
A15: OP-02 | B15: OP-J05 | C15: Pass | D15: 9 | E15: None
A16: OP-02 | B16: OP-J06 | C16: Pass | E16: None
A17: OP-02 | B17: OP-J07 | C17: Pass | E17: None
A18: OP-02 | B18: OP-J08 | C18: Pass | E18: None
A19: OP-02 | B19: OP-J09 | C19: Pass | E19: Verbal Prompt
A20: OP-03 | B20: OP-J01 | C20: Pass | E20: Verbal Prompt | F20: - the most hesitant among the participants kasi hindi raw siya marunong masyado sa computer yet nagawa naman niya nang tama with verbal prompts na expected na dahil mahirap yung scenarios?? | H20: [behind-the-scene photo/s link]
A21: OP-03 | B21: OP-J02 | C21: Pass | E21: Verbal Prompt
A22: OP-03 | B22: OP-J03 | C22: Pass | E22: Verbal Prompt
A23: OP-03 | B23: OP-J04 | C23: Pass | E23: Verbal Prompt
A24: OP-03 | B24: OP-J05 | C24: Pass | D24: 15 | E24: Verbal Prompt
A25: OP-03 | B25: OP-J06 | C25: Pass | E25: Verbal Prompt
A26: OP-03 | B26: OP-J07 | C26: Pass | E26: Verbal Prompt
A27: OP-03 | B27: OP-J08 | C27: Pass | E27: Verbal Prompt
A28: OP-03 | B28: OP-J09 | C28: Pass | E28: Verbal Prompt
A29: ADM-01 | B29: AD-J01 | C29: Pass | E29: None | F29: N/A | H29: [behind-the-scene photo/s link]
A30: ADM-01 | B30: AD-J02 | C30: Pass | E30: None
A31: ADM-01 | B31: AD-J03 | C31: Pass | E31: None
A32: ADM-01 | B32: AD-J04 | C32: Pass | E32: None
A33: ADM-01 | B33: AD-J05 | C33: Pass | E33: None
A34: ADM-01 | B34: AD-J06 | C34: Pass | E34: None

Sheet SUS Questionnaire
A1: System Usability Scale (SUS) Questionnaire
A2: Complete after the participant finishes the full role-based journey. Rate each statement from 1 (Strongly disagree) to 5 (Strongly agree). Use coded participant IDs only.
A3: Scoring: Q1, Q3, Q5, Q7, Q9 use rating − 1; Q2, Q4, Q6, Q8, Q10 use 5 − rating. Sum and multiply by 2.5.
A4: Participant ID | B4: Date | C4: Facilitator | D4: Q1: I think that I would like to use this system frequently. | E4: Q2: I found the system unnecessarily complex. | F4: Q3: I thought the system was easy to use. | G4: Q4: I think that I would need support from a technical person to use this system. | H4: Q5: I found the various functions in this system were well integrated. | I4: Q6: I thought there was too much inconsistency in this system. | J4: Q7: I would imagine that most people would learn to use this system very quickly. | K4: Q8: I found the system very cumbersome to use. | L4: Q9: I felt very confident using this system. | M4: Q10: I needed to learn a lot of things before I could get going with this system. | N4: SUS Score (0–100) | O4: Observation / Notes
A5: OP-01 | D5: 5 | E5: 3 | F5: 5 | G5: 5 | H5: 5 | I5: 1 | J5: 5 | K5: 1 | L5: 5 | M5: 1 | N5: =IF(COUNTA(D5:M5)<10,"",((D5-1)+(5-E5)+(F5-1)+(5-G5)+(H5-1)+(5-I5)+(J5-1)+(5-K5)+(L5-1)+(5-M5))*2.5) -> 85
A6: OP-02 | D6: 5 | E6: 1 | F6: 4 | G6: 1 | H6: 5 | I6: 1 | J6: 5 | K6: 2 | L6: 5 | M6: 1 | N6: =IF(COUNTA(D6:M6)<10,"",((D6-1)+(5-E6)+(F6-1)+(5-G6)+(H6-1)+(5-I6)+(J6-1)+(5-K6)+(L6-1)+(5-M6))*2.5) -> 95
A7: OP-03 | D7: 5 | E7: 2 | F7: 5 | G7: 3 | H7: 4 | I7: 2 | J7: 4 | K7: 2 | L7: 5 | M7: 3 | N7: =IF(COUNTA(D7:M7)<10,"",((D7-1)+(5-E7)+(F7-1)+(5-G7)+(H7-1)+(5-I7)+(J7-1)+(5-K7)+(L7-1)+(5-M7))*2.5) -> 77.5
A8: ADM-01 | D8: 5 | E8: 1 | F8: 5 | G8: 1 | H8: 5 | I8: 1 | J8: 5 | K8: 1 | L8: 5 | M8: 1 | N8: =IF(COUNTA(D8:M8)<10,"",((D8-1)+(5-E8)+(F8-1)+(5-G8)+(H8-1)+(5-I8)+(J8-1)+(5-K8)+(L8-1)+(5-M8))*2.5) -> 100
A10: SUS Summary | B10: Value
A11: Completed Responses | B11: =COUNT(N5:N8) -> 4
A12: Overall Mean | B12: =IFERROR(AVERAGE(N5:N8),"") -> 89.375
A13: Operator Mean | B13: =IFERROR(AVERAGE(N5:N7),"") -> 85.833333
A14: Administrator Mean | B14: =IFERROR(AVERAGE(N8),"") -> 100
A15: Median | B15: =IFERROR(MEDIAN(N5:N8),"") -> 90
A16: Minimum | B16: =IFERROR(MIN(N5:N8),"") -> 77.5
A17: Maximum | B17: =IFERROR(MAX(N5:N8),"") -> 100
A18: Acceptance Criterion | B18: 68
A19: Criterion Status | B19: Pass

Sheet UAT Results
A1: UAT Results
A2: Calculated from the shared participant-stage Execution Log, SUS Questionnaire, Defect Log, and Session Control.
A3: Metric | B3: Value | C3: Criterion | D3: Gate Status
A4: Planned applicable participant-stage executions | B4: =COUNTA('Execution Log'!A2:A34) -> 33 | C4: 33 | D4: =IF(B4=33,"Pass","Check") -> Pass
A5: Completed final executions | B5: =COUNTIF('Execution Log'!C2:C34,"Pass")+COUNTIF('Execution Log'!C2:C34,"Fail") -> 33 | C5: 33 | D5: =IF(B5=B4,"Pass","Pending") -> Pass
A6: Passed executions | B6: =COUNTIF('Execution Log'!C2:C34,"Pass") -> 33 | C6: Report count | D6: Information
A7: Participant-stage pass rate | B7: =IFERROR(B6/B4,0) -> 1 | C7: >=95% | D7: =IF(B7>=0.95,"Pass","Pending/Fail") -> Pass
A8: Incomplete / unresolved executions | B8: =COUNTIF('Execution Log'!C2:C34,"Not Executed")+COUNTIF('Execution Log'!C2:C34,"Blocked")+COUNTIF('Execution Log'!C2:C34,"Retest Required") -> 0 | C8: 0 | D8: =IF(B8=0,"Pass","Pending") -> Pass
A9: Failed completed executions | B9: =COUNTIF('Execution Log'!C2:C34,"Fail") -> 0 | C9: Report count; maximum 3 when all 33 are final | D9: =IF(B8>0,"Pending",IF(B9<=3,"Within numerical threshold","Below 95%")) -> Within numerical threshold
A10: Open Critical or Major defects | B10: =COUNTIFS('Defect Log'!A2:A100,"<>",'Defect Log'!D2:D100,"Critical",'Defect Log'!E2:E100,"<>Closed")+COUNTIFS('Defect Log'!A2:A100,"<>",'Defect Log'!D2:D100,"Major",'Defect Log'!E2:E100,"<>Closed") -> 0 | C10: 0 | D10: =IF(B10=0,"Pass","Blocked") -> Pass
A11: Overall SUS mean | B11: =IFERROR(AVERAGE('SUS Questionnaire'!N5:N8),0) -> 89.375 | C11: >=68 | D11: =IF(B11>=68,"Pass","Pending/Fail") -> Pass
A12: Readiness items marked Ready | B12: =COUNTIF('Session Control'!C21:C29,"Ready") -> 9 | C12: 9 | D12: =IF(B12=9,"Pass","Pending") -> Pass
A13: Eligibility for formal sign-off | B13: =IF(AND(B4=33,B5=B4,B8=0,B7>=0.95,B10=0,B11>=68,B12=9),"ELIGIBLE FOR FORMAL SIGN-OFF","NOT YET ELIGIBLE") -> ELIGIBLE FOR FORMAL SIGN-OFF | C13: Every gate above must pass | D13: =B13 -> ELIGIBLE FOR FORMAL SIGN-OFF
A14: Formal Acceptance Decision | B14: ='Session Control'!B12 -> Accepted | C14: Pending / Accepted / Accepted with Conditions / Rejected | D14: Manual decision in signed document
A16: Interpretation | B16: The 95% calculation uses all planned applicable participant-stage executions. A missing execution reduces completeness and prevents eligibility; it is never removed from the denominator.

Sheet Usability Results
A1: Usability Results
A2: These results reuse the shared Execution Log; no task is entered twice.
A4: Participant ID | B4: Planned Stages | C4: Pass | D4: Needs Attention | E4: Alert-to-Decision Seconds (raw) | F4: Assistance Events | G4: SUS Score | H4: Learnability Minutes
A5: OP-01 | B5: =COUNTIF('Execution Log'!A:A,A5) -> 9 | C5: =COUNTIFS('Execution Log'!A:A,A5,'Execution Log'!C:C,"Pass") -> 9 | D5: =COUNTIFS('Execution Log'!A:A,A5,'Execution Log'!C:C,"<>Pass",'Execution Log'!C:C,"<>Not Executed") -> 0 | E5: =IFERROR(AVERAGEIFS('Execution Log'!D:D,'Execution Log'!A:A,A5,'Execution Log'!B:B,"OP-J05"),"") -> 16 | F5: =COUNTIFS('Execution Log'!A:A,A5,'Execution Log'!E:E,"<>",'Execution Log'!E:E,"<>None") -> 9 | G5: =IFERROR(VLOOKUP(A5,'SUS Questionnaire'!A:N,14,FALSE()),"") -> 85 | H5: =IFERROR(VLOOKUP(A5,'Session Control'!A:E,5,FALSE()),"") -> 5
A6: OP-02 | B6: =COUNTIF('Execution Log'!A:A,A6) -> 9 | C6: =COUNTIFS('Execution Log'!A:A,A6,'Execution Log'!C:C,"Pass") -> 9 | D6: =COUNTIFS('Execution Log'!A:A,A6,'Execution Log'!C:C,"<>Pass",'Execution Log'!C:C,"<>Not Executed") -> 0 | E6: =IFERROR(AVERAGEIFS('Execution Log'!D:D,'Execution Log'!A:A,A6,'Execution Log'!B:B,"OP-J05"),"") -> 9 | F6: =COUNTIFS('Execution Log'!A:A,A6,'Execution Log'!E:E,"<>",'Execution Log'!E:E,"<>None") -> 1 | G6: =IFERROR(VLOOKUP(A6,'SUS Questionnaire'!A:N,14,FALSE()),"") -> 95 | H6: =IFERROR(VLOOKUP(A6,'Session Control'!A:E,5,FALSE()),"") -> 5
A7: OP-03 | B7: =COUNTIF('Execution Log'!A:A,A7) -> 9 | C7: =COUNTIFS('Execution Log'!A:A,A7,'Execution Log'!C:C,"Pass") -> 9 | D7: =COUNTIFS('Execution Log'!A:A,A7,'Execution Log'!C:C,"<>Pass",'Execution Log'!C:C,"<>Not Executed") -> 0 | E7: =IFERROR(AVERAGEIFS('Execution Log'!D:D,'Execution Log'!A:A,A7,'Execution Log'!B:B,"OP-J05"),"") -> 15 | F7: =COUNTIFS('Execution Log'!A:A,A7,'Execution Log'!E:E,"<>",'Execution Log'!E:E,"<>None") -> 9 | G7: =IFERROR(VLOOKUP(A7,'SUS Questionnaire'!A:N,14,FALSE()),"") -> 77.5 | H7: =IFERROR(VLOOKUP(A7,'Session Control'!A:E,5,FALSE()),"") -> 5
A8: ADM-01 | B8: =COUNTIF('Execution Log'!A:A,A8) -> 6 | C8: =COUNTIFS('Execution Log'!A:A,A8,'Execution Log'!C:C,"Pass") -> 6 | D8: =COUNTIFS('Execution Log'!A:A,A8,'Execution Log'!C:C,"<>Pass",'Execution Log'!C:C,"<>Not Executed") -> 0 | E8: =IFERROR(AVERAGEIFS('Execution Log'!D:D,'Execution Log'!A:A,A8,'Execution Log'!B:B,"OP-J05"),"") | F8: =COUNTIFS('Execution Log'!A:A,A8,'Execution Log'!E:E,"<>",'Execution Log'!E:E,"<>None") -> 0 | G8: =IFERROR(VLOOKUP(A8,'SUS Questionnaire'!A:N,14,FALSE()),"") -> 100 | H8: =IFERROR(VLOOKUP(A8,'Session Control'!A:E,5,FALSE()),"") -> 5
A10: Overall Usability Metric | B10: Value | C10: Interpretation
A11: Completed SUS responses | B11: =COUNT('SUS Questionnaire'!N5:N8) -> 4 | C11: Target: 4
A12: Overall SUS mean | B12: =IFERROR(AVERAGE('SUS Questionnaire'!N5:N8),"") -> 89.375 | C12: Target: >=68
A13: Operator SUS mean | B13: =IFERROR(AVERAGE('SUS Questionnaire'!N5:N7),"") -> 85.833333 | C13: Descriptive subgroup result
A14: Administrator SUS mean | B14: =IFERROR(AVERAGE('SUS Questionnaire'!N8),"") -> 100 | C14: Descriptive subgroup result
A15: OP-J05 NFR-09 estimated mean (alert-to-decision + 3 s + 2 s) | B15: =IFERROR(AVERAGEIF('Execution Log'!B:B,"OP-J05",'Execution Log'!D:D)+3+2,"") -> 18.333333 | C15: NFR-09: <=25 seconds
A16: OP-J05 NFR-09 estimated worst case (alert-to-decision + 3 s + 2 s) | B16: =IFERROR(__xludf.DUMMYFUNCTION("IFERROR(MAX(FILTER('Execution Log'!D:D,'Execution Log'!B:B=""OP-J05"",'Execution Log'!D:D<>""""))+3+2,"""")"),21.0) -> 21 | C16: Report alongside mean
A17: First-time users meeting learnability | B17: =COUNTIFS('Session Control'!C15:C18,"Yes",'Session Control'!E15:E18,"<=15") -> 4 | C17: NFR-12: <=15 minutes after briefing
A18: First-time users assessed | B18: =COUNTIF('Session Control'!C15:C18,"Yes") -> 4 | C18: Report denominator

Sheet Defect Log
A1: Defect ID | B1: Stage / Source | C1: Description | D1: Severity | E1: Status | F1: Resolution / Retest Notes | G1: Evidence Link

Sheet UAT Traceability
A1: Type | B1: ID | C1: Requirement / Objective | D1: UAT Journey Stage(s) or Technical Source | E1: Execution / Evidence Location | F1: Coverage Status | G1: Notes
A2: Functional Requirement | B2: FR-01 | C2: User Authentication | D2: OP-J01; AD-J01 | E2: Execution Log; linked evidence | F2: Mapped | G2: All user-facing FRs have a role-appropriate journey stage.
A3: Functional Requirement | B3: FR-02 | C3: Role-Based Access Control (RBAC) | D3: OP-J01; AD-J01; AD-J03 | E3: Execution Log; linked evidence | F3: Mapped | G3: All user-facing FRs have a role-appropriate journey stage.
A4: Functional Requirement | B4: FR-03 | C4: User Account Management | D4: AD-J03 | E4: Execution Log; linked evidence | F4: Mapped | G4: All user-facing FRs have a role-appropriate journey stage.
A5: Functional Requirement | B5: FR-04 | C5: Video Stream Ingestion | D5: OP-J04 | E5: Execution Log; linked evidence | F5: Mapped | G5: All user-facing FRs have a role-appropriate journey stage.
A6: Functional Requirement | B6: FR-05 | C6: Automated Collision Detection | D6: OP-J04 | E6: Execution Log; linked evidence | F6: Mapped | G6: All user-facing FRs have a role-appropriate journey stage.
A7: Functional Requirement | B7: FR-06 | C7: Alert Generation and Snapshot Capture | D7: OP-J04 | E7: Execution Log; linked evidence | F7: Mapped | G7: All user-facing FRs have a role-appropriate journey stage.
A8: Functional Requirement | B8: FR-07 | C8: Audible Alert Timeout and Escalation | D8: OP-J02; OP-J05; OP-J06 | E8: Execution Log; linked evidence | F8: Mapped | G8: UAT observes alarm configuration, one global Snooze action, and re-alarm when expiry remains observable; deterministic timeout proof also belongs in technical System/E2E testing.
A9: Functional Requirement | B9: FR-08 | C9: Alarm Configuration Module | D9: OP-J02 | E9: Execution Log; linked evidence | F9: Mapped | G9: All user-facing FRs have a role-appropriate journey stage.
A10: Functional Requirement | B10: FR-09 | C10: Human-in-the-Loop Verification Workflow | D10: OP-J05; OP-J06 | E10: Execution Log; linked evidence | F10: Mapped | G10: All user-facing FRs have a role-appropriate journey stage.
A11: Functional Requirement | B11: FR-10 | C11: False Positive Handling | D11: OP-J06 | E11: Execution Log; linked evidence | F11: Mapped | G11: All user-facing FRs have a role-appropriate journey stage.
A12: Functional Requirement | B12: FR-11 | C12: True Positive Handling | D12: OP-J05; OP-J07 | E12: Execution Log; linked evidence | F12: Mapped | G12: All user-facing FRs have a role-appropriate journey stage.
... A38: Non-Functional Requirement | B38: NFR-18 | C38: Data Redundancy & Recovery | D38: AD-J04; AD-J05; Backup & Recovery (TC-BR-001–TC-BR-005) | E38: Backup & Recovery; Execution Log / Session Control; linked evidence | F38: Mapped | G38: UAT evaluates understandable tier-labeled backup selection, restoration safeguards, restored state, and fresh post-recovery alerting. Protected-versus-degraded fallback warnings and the local rollback reserve are covered by the technical Backup & Recovery activity; the strict 60-second recovery measurement remains there.
A39: Non-Functional Requirement | B39: NFR-19 | C39: Session Security | D39: Security Testing | F39: Mapped | G39: Not forced into UAT; must be proven by the named technical activity before UAT readiness.
A40: Non-Functional Requirement | B40: NFR-20 | C40: Data Localization | D40: Security Testing | E40: Named technical activity tab; evidence link | F40: Mapped | G40: Not forced into UAT; must be proven by the named technical activity before UAT readiness.
A41: Non-Functional Requirement | B41: NFR-21 | C41: Audit Trail Integrity | D41: AD-J06; Security Testing | E41: Execution Log / Session Control; linked evidence | F41: Mapped | G41: Observed during participant journey; technical measurements remain separate where applicable.
A42: Non-Functional Requirement | B42: NFR-22 | C42: Modular AI Upgrades | D42: AI Model Validation; Integration Testing | E42: Named technical activity tab; evidence link | F42: Mapped | G42: Not forced into UAT; must be proven by the named technical activity before UAT readiness.
A43: Acceptance Criterion | B43: AC-USE | C43: Overall SUS mean >=68 | D43: SUS Questionnaire; Usability Results | E43: SUS response rows and calculated summary | F43: Mapped | G43: Eight participants: six Operators and two Administrators.
A44: Acceptance Criterion | B44: AC-UAT | C44: Clarified UAT execution rule | D44: UAT Results | E44: Execution Log; Defect Log; Session Control; sign-off document | F44: New Addition | G44: New Codex proposal; highlighted and noted in Summary and UAT Results.
